{
  "tracks": [
    {
      "artist": "ATR ANSAMBLİ",
      "title": "boyka qaytarması",
      "db_artist": "ATR ansambli",
      "path": "/Volumes/T9/1_dev/1_QO/myQO/navidrome/scripts/vk-music-scanner/downloads/ATR ansambli/ATR ANSAMBLİ - boyka qaytarması.mp3",
      "downloaded_at": "2025-12-25T11:18:06.932088"
    },
    {
      "artist": "ATR ANSAMBLİ",
      "title": "seydane köz ve qaytarma",
      "db_artist": "ATR ansambli",
      "path": "/Volumes/T9/1_dev/1_QO/myQO/navidrome/scripts/vk-music-scanner/downloads/ATR ansambli/ATR ANSAMBLİ - seydane köz ve qaytarma.mp3",
      "downloaded_at": "2025-12-25T11:18:11.354072"
    },
    {
      "artist": "ATR ansambli",
      "title": "Qızlar oyunı ve haytarma",
      "db_artist": "ATR ansambli",
      "path": "/Volumes/T9/1_dev/1_QO/myQO/navidrome/scripts/vk-music-scanner/downloads/ATR ansambli/ATR ansambli - Qızlar oyunı ve haytarma.mp3",
      "downloaded_at": "2025-12-25T11:18:14.701082"
    },
    {
      "artist": "ATR ANSAMBLİ VE ASAN BİLÂLOV",
      "title": "men bostancı degilim",
      "db_artist": "ATR ansambli",
      "path": "/Volumes/T9/1_dev/1_QO/myQO/navidrome/scripts/vk-music-scanner/downloads/ATR ansambli/ATR ANSAMBLİ VE ASAN BİLÂLOV - men bostancı degilim.mp3",
      "downloaded_at": "2025-12-25T11:18:22.944378"
    },
    {
      "artist": "ATR ANSAMBLİ",
      "title": "Bağçasaray tabana dolusı",
      "db_artist": "ATR ansambli",
      "path": "/Volumes/T9/1_dev/1_QO/myQO/navidrome/scripts/vk-music-scanner/downloads/ATR ansambli/ATR ANSAMBLİ - Bağçasaray tabana dolusı.mp3",
      "downloaded_at": "2025-12-25T11:18:25.920146"
    },
    {
      "artist": "ATR ANSAMBLİ",
      "title": "ağır ava ve qaytarma",
      "db_artist": "ATR ansambli",
      "path": "/Volumes/T9/1_dev/1_QO/myQO/navidrome/scripts/vk-music-scanner/downloads/ATR ansambli/ATR ANSAMBLİ - ağır ava ve qaytarma.mp3",
      "downloaded_at": "2025-12-25T11:18:28.839160"
    },
    {
      "artist": "ATR ansambli",
      "title": "Ag?r ava ve haytarma",
      "db_artist": "ATR ansambli",
      "path": "/Volumes/T9/1_dev/1_QO/myQO/navidrome/scripts/vk-music-scanner/downloads/ATR ansambli/ATR ansambli - Ag_r ava ve haytarma.mp3",
      "downloaded_at": "2025-12-25T11:18:31.118923"
    },
    {
      "artist": "Asan Umerov ve ATR ansambli",
      "title": "Şamatalı kelin",
      "db_artist": "ATR ansambli",
      "path": "/Volumes/T9/1_dev/1_QO/myQO/navidrome/scripts/vk-music-scanner/downloads/ATR ansambli/Asan Umerov ve ATR ansambli - Şamatalı kelin.mp3",
      "downloaded_at": "2025-12-25T11:18:33.988121"
    },
    {
      "artist": "ATR ANSAMBLİ",
      "title": "bereket oyun avası",
      "db_artist": "ATR ansambli",
      "path": "/Volumes/T9/1_dev/1_QO/myQO/navidrome/scripts/vk-music-scanner/downloads/ATR ansambli/ATR ANSAMBLİ - bereket oyun avası.mp3",
      "downloaded_at": "2025-12-25T11:19:51.482794"
    },
    {
      "artist": "Elzara Batalova ve ATR ansambli",
      "title": "Dağlarnıñ yolları (live)",
      "db_artist": "ATR ansambli",
      "path": "/Volumes/T9/1_dev/1_QO/myQO/navidrome/scripts/vk-music-scanner/downloads/ATR ansambli/Elzara Batalova ve ATR ansambli - Dağlarnıñ yolları (live).mp3",
      "downloaded_at": "2025-12-25T11:19:55.975858"
    },
    {
      "artist": "Asan Bilâlov ve ATR ansambli",
      "title": "İstanbuldan nar gelir",
      "db_artist": "ATR ansambli",
      "path": "/Volumes/T9/1_dev/1_QO/myQO/navidrome/scripts/vk-music-scanner/downloads/ATR ansambli/Asan Bilâlov ve ATR ansambli - İstanbuldan nar gelir.mp3",
      "downloaded_at": "2025-12-25T11:19:58.490603"
    },
    {
      "artist": "ATR ANSAMBLİ VE ALİM OSMANOV",
      "title": "er dilde bitmez nağmesı",
      "db_artist": "ATR ansambli",
      "path": "/Volumes/T9/1_dev/1_QO/myQO/navidrome/scripts/vk-music-scanner/downloads/ATR ansambli/ATR ANSAMBLİ VE ALİM OSMANOV - er dilde bitmez nağmesı.mp3",
      "downloaded_at": "2025-12-25T11:20:02.481930"
    },
    {
      "artist": "Afize Kassara",
      "title": "O koz'lerin yaqti beni",
      "db_artist": "Afize Kassara",
      "path": "/Volumes/T9/1_dev/1_QO/myQO/navidrome/scripts/vk-music-scanner/downloads/Afize Kassara/Afize Kassara - O koz'lerin yaqti beni.mp3",
      "downloaded_at": "2025-12-25T11:20:09.995429"
    },
    {
      "artist": "Afize Kassara",
      "title": "Men Giderim Batuma",
      "db_artist": "Afize Kassara",
      "path": "/Volumes/T9/1_dev/1_QO/myQO/navidrome/scripts/vk-music-scanner/downloads/Afize Kassara/Afize Kassara - Men Giderim Batuma.mp3",
      "downloaded_at": "2025-12-25T11:20:12.770230"
    },
    {
      "artist": "Afize Kassara",
      "title": "Ak Deniz Kenarinda",
      "db_artist": "Afize Kassara",
      "path": "/Volumes/T9/1_dev/1_QO/myQO/navidrome/scripts/vk-music-scanner/downloads/Afize Kassara/Afize Kassara - Ak Deniz Kenarinda.mp3",
      "downloaded_at": "2025-12-25T11:20:18.502650"
    },
    {
      "artist": "Afize Kassara",
      "title": "Uch qaranfil",
      "db_artist": "Afize Kassara",
      "path": "/Volumes/T9/1_dev/1_QO/myQO/navidrome/scripts/vk-music-scanner/downloads/Afize Kassara/Afize Kassara - Uch qaranfil.mp3",
      "downloaded_at": "2025-12-25T11:20:20.898403"
    },
    {
      "artist": "Afize Kassara ve Maqam",
      "title": "Bağçalarda kestane (Live)",
      "db_artist": "Afize Kassara",
      "path": "/Volumes/T9/1_dev/1_QO/myQO/navidrome/scripts/vk-music-scanner/downloads/Afize Kassara/Afize Kassara ve Maqam - Bağçalarda kestane (Live).mp3",
      "downloaded_at": "2025-12-25T11:20:23.439538"
    },
    {
      "artist": "Afize Kassara",
      "title": "Odjaq Bashi",
      "db_artist": "Afize Kassara",
      "path": "/Volumes/T9/1_dev/1_QO/myQO/navidrome/scripts/vk-music-scanner/downloads/Afize Kassara/Afize Kassara - Odjaq Bashi.mp3",
      "downloaded_at": "2025-12-25T11:20:30.532204"
    },
    {
      "artist": "Seyran7--39-62 ve Afize Yusuf-Qızı",
      "title": "Qırımda yaşa",
      "db_artist": "Afize Yusuf-qızı",
      "path": "/Volumes/T9/1_dev/1_QO/myQO/navidrome/scripts/vk-music-scanner/downloads/Afize Yusuf-qızı/Seyran7--39-62 ve Afize Yusuf-Qızı - Qırımda yaşa.mp3",
      "downloaded_at": "2025-12-25T11:20:39.916474"
    },
    {
      "artist": "Seyran7'62 ve Afize Yusuf-Qızı",
      "title": "Qırımda yaşa",
      "db_artist": "Afize Yusuf-qızı",
      "path": "/Volumes/T9/1_dev/1_QO/myQO/navidrome/scripts/vk-music-scanner/downloads/Afize Yusuf-qızı/Seyran7'62 ve Afize Yusuf-Qızı - Qırımda yaşa.mp3",
      "downloaded_at": "2025-12-25T11:20:43.141070"
    },
    {
      "artist": "Afize Yusuf-qızı",
      "title": "Vatan asreti (n)",
      "db_artist": "Afize Yusuf-qızı",
      "path": "/Volumes/T9/1_dev/1_QO/myQO/navidrome/scripts/vk-music-scanner/downloads/Afize Yusuf-qızı/Afize Yusuf-qızı - Vatan asreti (n).mp3",
      "downloaded_at": "2025-12-25T11:20:45.927479"
    },
    {
      "artist": "Afize Yusuf-qızı",
      "title": "BAHAR KELSE (2014)",
      "db_artist": "Afize Yusuf-qızı",
      "path": "/Volumes/T9/1_dev/1_QO/myQO/navidrome/scripts/vk-music-scanner/downloads/Afize Yusuf-qızı/Afize Yusuf-qızı - BAHAR KELSE (2014).mp3",
      "downloaded_at": "2025-12-25T11:20:48.432828"
    },
    {
      "artist": "Afize Yusuf-qızı",
      "title": "Ereсebim",
      "db_artist": "Afize Yusuf-qızı",
      "path": "/Volumes/T9/1_dev/1_QO/myQO/navidrome/scripts/vk-music-scanner/downloads/Afize Yusuf-qızı/Afize Yusuf-qızı - Ereсebim.mp3",
      "downloaded_at": "2025-12-25T11:20:51.338463"
    },
    {
      "artist": "Afize Yusuf-qızı",
      "title": "Alim, Alim demekten",
      "db_artist": "Afize Yusuf-qızı",
      "path": "/Volumes/T9/1_dev/1_QO/myQO/navidrome/scripts/vk-music-scanner/downloads/Afize Yusuf-qızı/Afize Yusuf-qızı - Alim, Alim demekten.mp3",
      "downloaded_at": "2025-12-25T11:20:53.712193"
    },
    {
      "artist": "Afize Yusuf-qızı",
      "title": "Dua",
      "db_artist": "Afize Yusuf-qızı",
      "path": "/Volumes/T9/1_dev/1_QO/myQO/navidrome/scripts/vk-music-scanner/downloads/Afize Yusuf-qızı/Afize Yusuf-qızı - Dua.mp3",
      "downloaded_at": "2025-12-25T11:20:58.184987"
    },
    {
      "artist": "Afize Yusuf-qızı",
      "title": "Qadifeden kisesi (2012)",
      "db_artist": "Afize Yusuf-qızı",
      "path": "/Volumes/T9/1_dev/1_QO/myQO/navidrome/scripts/vk-music-scanner/downloads/Afize Yusuf-qızı/Afize Yusuf-qızı - Qadifeden kisesi (2012).mp3",
      "downloaded_at": "2025-12-25T11:21:01.246253"
    },
    {
      "artist": "Alim Osmanov (Qara Deñiz)",
      "title": "Севастополь",
      "db_artist": "Alim Osmanov (Qara Deñiz)",
      "path": "/Volumes/T9/1_dev/1_QO/myQO/navidrome/scripts/vk-music-scanner/downloads/Alim Osmanov (Qara Deñiz)/Alim Osmanov (Qara Deñiz) - Севастополь.mp3",
      "downloaded_at": "2025-12-25T11:22:19.821260"
    },
    {
      "artist": "Arsen Kursaitov",
      "title": "В последний раз (2015) (Prod.by FortRoyalBeatz)",
      "db_artist": "Arsen Kursaitov",
      "path": "/Volumes/T9/1_dev/1_QO/myQO/navidrome/scripts/vk-music-scanner/downloads/Arsen Kursaitov/Arsen Kursaitov - В последний раз (2015) (Prod.by FortRoyalBeatz).mp3",
      "downloaded_at": "2025-12-25T11:22:22.560661"
    },
    {
      "artist": "Arsen Kursaitov",
      "title": "Ne razlubit'",
      "db_artist": "Arsen Kursaitov",
      "path": "/Volumes/T9/1_dev/1_QO/myQO/navidrome/scripts/vk-music-scanner/downloads/Arsen Kursaitov/Arsen Kursaitov - Ne razlubit'.mp3",
      "downloaded_at": "2025-12-25T11:22:24.576998"
    },
    {
      "artist": "Arsen Kursaitov",
      "title": "Bir Anam",
      "db_artist": "Arsen Kursaitov",
      "path": "/Volumes/T9/1_dev/1_QO/myQO/navidrome/scripts/vk-music-scanner/downloads/Arsen Kursaitov/Arsen Kursaitov - Bir Anam.mp3",
      "downloaded_at": "2025-12-25T11:22:26.648417"
    },
    {
      "artist": "Arsen Kursaitov",
      "title": "V radosti,v razluke!",
      "db_artist": "Arsen Kursaitov",
      "path": "/Volumes/T9/1_dev/1_QO/myQO/navidrome/scripts/vk-music-scanner/downloads/Arsen Kursaitov/Arsen Kursaitov - V radosti,v razluke!.mp3",
      "downloaded_at": "2025-12-25T11:22:28.802582"
    },
    {
      "artist": "Arsen Kursaitov",
      "title": "Ne iapaim",
      "db_artist": "Arsen Kursaitov",
      "path": "/Volumes/T9/1_dev/1_QO/myQO/navidrome/scripts/vk-music-scanner/downloads/Arsen Kursaitov/Arsen Kursaitov - Ne iapaim.mp3",
      "downloaded_at": "2025-12-25T11:22:31.184716"
    },
    {
      "artist": "ARSEN KURSAITOV",
      "title": "биль анам!",
      "db_artist": "Arsen Kursaitov",
      "path": "/Volumes/T9/1_dev/1_QO/myQO/navidrome/scripts/vk-music-scanner/downloads/Arsen Kursaitov/ARSEN KURSAITOV - биль анам!.mp3",
      "downloaded_at": "2025-12-25T11:22:33.556584"
    },
    {
      "artist": "Arsen Kursaitov",
      "title": "Kamiwim",
      "db_artist": "Arsen Kursaitov",
      "path": "/Volumes/T9/1_dev/1_QO/myQO/navidrome/scripts/vk-music-scanner/downloads/Arsen Kursaitov/Arsen Kursaitov - Kamiwim.mp3",
      "downloaded_at": "2025-12-25T11:22:35.937940"
    },
    {
      "artist": "arsen kursaitov i alie dzhivan",
      "title": "ketme dzhanym",
      "db_artist": "Arsen Kursaitov",
      "path": "/Volumes/T9/1_dev/1_QO/myQO/navidrome/scripts/vk-music-scanner/downloads/Arsen Kursaitov/arsen kursaitov i alie dzhivan - ketme dzhanym.mp3",
      "downloaded_at": "2025-12-25T11:22:38.809095"
    },
    {
      "artist": "Arsen Kursaitov",
      "title": "Añlatsa",
      "db_artist": "Arsen Kursaitov",
      "path": "/Volumes/T9/1_dev/1_QO/myQO/navidrome/scripts/vk-music-scanner/downloads/Arsen Kursaitov/Arsen Kursaitov - Añlatsa.mp3",
      "downloaded_at": "2025-12-25T11:22:43.379082"
    },
    {
      "artist": "Arsen Kursaitov",
      "title": "sevginin lezeti",
      "db_artist": "Arsen Kursaitov",
      "path": "/Volumes/T9/1_dev/1_QO/myQO/navidrome/scripts/vk-music-scanner/downloads/Arsen Kursaitov/Arsen Kursaitov - sevginin lezeti.mp3",
      "downloaded_at": "2025-12-25T11:22:45.416569"
    },
    {
      "artist": "Arsen Kursaitov",
      "title": "Kamin",
      "db_artist": "Arsen Kursaitov",
      "path": "/Volumes/T9/1_dev/1_QO/myQO/navidrome/scripts/vk-music-scanner/downloads/Arsen Kursaitov/Arsen Kursaitov - Kamin.mp3",
      "downloaded_at": "2025-12-25T11:22:47.480698"
    },
    {
      "artist": "Arsen Kursaitov feat Lenie Djepparova",
      "title": "Bol' razluki",
      "db_artist": "Arsen Kursaitov",
      "path": "/Volumes/T9/1_dev/1_QO/myQO/navidrome/scripts/vk-music-scanner/downloads/Arsen Kursaitov/Arsen Kursaitov feat Lenie Djepparova - Bol' razluki.mp3",
      "downloaded_at": "2025-12-25T11:22:49.981440"
    },
    {
      "artist": "Arsen Kursaitov x ЭмДжиЭл",
      "title": "Eki Yurek (feat. STZ) (Shahunts Brothers cover)",
      "db_artist": "Arsen Kursaitov",
      "path": "/Volumes/T9/1_dev/1_QO/myQO/navidrome/scripts/vk-music-scanner/downloads/Arsen Kursaitov/Arsen Kursaitov x ЭмДжиЭл - Eki Yurek (feat. STZ) (Shahunts Brothers cover).mp3",
      "downloaded_at": "2025-12-25T11:22:54.300970"
    },
    {
      "artist": "Arsen Kursaitov",
      "title": "Sevginiñ lezzeti",
      "db_artist": "Arsen Kursaitov",
      "path": "/Volumes/T9/1_dev/1_QO/myQO/navidrome/scripts/vk-music-scanner/downloads/Arsen Kursaitov/Arsen Kursaitov - Sevginiñ lezzeti.mp3",
      "downloaded_at": "2025-12-25T11:22:56.568397"
    },
    {
      "artist": "Arsen Kursaitov",
      "title": "Сказка без конца(Cover-Lirik version)",
      "db_artist": "Arsen Kursaitov",
      "path": "/Volumes/T9/1_dev/1_QO/myQO/navidrome/scripts/vk-music-scanner/downloads/Arsen Kursaitov/Arsen Kursaitov - Сказка без конца(Cover-Lirik version).mp3",
      "downloaded_at": "2025-12-25T11:22:59.528823"
    },
    {
      "artist": "Arsen Osmanov",
      "title": "Озен баш",
      "db_artist": "Arsen Osmanov",
      "path": "/Volumes/T9/1_dev/1_QO/myQO/navidrome/scripts/vk-music-scanner/downloads/Arsen Osmanov/Arsen Osmanov - Озен баш.mp3",
      "downloaded_at": "2025-12-25T11:23:03.906768"
    },
    {
      "artist": "Arsen Osmanov",
      "title": "Çanaqqale",
      "db_artist": "Arsen Osmanov",
      "path": "/Volumes/T9/1_dev/1_QO/myQO/navidrome/scripts/vk-music-scanner/downloads/Arsen Osmanov/Arsen Osmanov - Çanaqqale.mp3",
      "downloaded_at": "2025-12-25T11:23:10.104614"
    },
    {
      "artist": "Arsen Osmanov & Mavile Sarana",
      "title": "Два любящих сердца",
      "db_artist": "Arsen Osmanov",
      "path": "/Volumes/T9/1_dev/1_QO/myQO/navidrome/scripts/vk-music-scanner/downloads/Arsen Osmanov/Arsen Osmanov & Mavile Sarana - Два любящих сердца.mp3",
      "downloaded_at": "2025-12-25T11:23:18.828571"
    },
    {
      "artist": "☆ ARSEN OSMANOV & SAFIE DENISHAEVA ☆ 2019",
      "title": "«OMURIMDE SENSIN»",
      "db_artist": "Arsen Osmanov",
      "path": "/Volumes/T9/1_dev/1_QO/myQO/navidrome/scripts/vk-music-scanner/downloads/Arsen Osmanov/☆ ARSEN OSMANOV & SAFIE DENISHAEVA ☆ 2019 - «OMURIMDE SENSIN».mp3",
      "downloaded_at": "2025-12-25T11:23:22.612902"
    },
    {
      "artist": "Arsen Osmanov",
      "title": "Bomba",
      "db_artist": "Arsen Osmanov",
      "path": "/Volumes/T9/1_dev/1_QO/myQO/navidrome/scripts/vk-music-scanner/downloads/Arsen Osmanov/Arsen Osmanov - Bomba.mp3",
      "downloaded_at": "2025-12-25T11:23:26.150561"
    },
    {
      "artist": "Arsen Osmanov & \"Hayat\"",
      "title": "2015 Qirimtatar",
      "db_artist": "Arsen Osmanov",
      "path": "/Volumes/T9/1_dev/1_QO/myQO/navidrome/scripts/vk-music-scanner/downloads/Arsen Osmanov/Arsen Osmanov & _Hayat_ - 2015 Qirimtatar.mp3",
      "downloaded_at": "2025-12-25T11:23:28.995537"
    },
    {
      "artist": "ARSEN OSMANOV",
      "title": "ALLAHIM NEYDI GÜNAHIM  2023.г.",
      "db_artist": "Arsen Osmanov",
      "path": "/Volumes/T9/1_dev/1_QO/myQO/navidrome/scripts/vk-music-scanner/downloads/Arsen Osmanov/ARSEN OSMANOV - ALLAHIM NEYDI GÜNAHIM  2023.г.mp3",
      "downloaded_at": "2025-12-25T11:23:32.359726"
    },
    {
      "artist": "Arsen Osmanov",
      "title": "Alchachik Evin 2020",
      "db_artist": "Arsen Osmanov",
      "path": "/Volumes/T9/1_dev/1_QO/myQO/navidrome/scripts/vk-music-scanner/downloads/Arsen Osmanov/Arsen Osmanov - Alchachik Evin 2020.mp3",
      "downloaded_at": "2025-12-25T11:23:34.698113"
    },
    {
      "artist": "ARSEN OSMANOV",
      "title": "\" KEREM \"",
      "db_artist": "Arsen Osmanov",
      "path": "/Volumes/T9/1_dev/1_QO/myQO/navidrome/scripts/vk-music-scanner/downloads/Arsen Osmanov/ARSEN OSMANOV - _ KEREM _.mp3",
      "downloaded_at": "2025-12-25T11:23:38.603283"
    },
    {
      "artist": "Asan Hayretdinov",
      "title": "Vatanım (Ringtone)",
      "db_artist": "Asan Hayretdinov",
      "path": "/Volumes/T9/1_dev/1_QO/myQO/navidrome/scripts/vk-music-scanner/downloads/Asan Hayretdinov/Asan Hayretdinov - Vatanım (Ringtone).mp3",
      "downloaded_at": "2025-12-25T11:23:41.061475"
    },
    {
      "artist": "Asiye Saale, Nariman Balich",
      "title": "Ay, çalaşım",
      "db_artist": "Asiye Saale",
      "path": "/Volumes/T9/1_dev/1_QO/myQO/navidrome/scripts/vk-music-scanner/downloads/Asiye Saale/Asiye Saale, Nariman Balich - Ay, çalaşım.mp3",
      "downloaded_at": "2025-12-25T11:23:44.732082"
    },
    {
      "artist": "Asiye Saale",
      "title": "Girdim yarın bağçasına",
      "db_artist": "Asiye Saale",
      "path": "/Volumes/T9/1_dev/1_QO/myQO/navidrome/scripts/vk-music-scanner/downloads/Asiye Saale/Asiye Saale - Girdim yarın bağçasına.mp3",
      "downloaded_at": "2025-12-25T11:23:48.276493"
    },
    {
      "artist": "Asiye Saale",
      "title": "Yaşa menim halqım! (live)",
      "db_artist": "Asiye Saale",
      "path": "/Volumes/T9/1_dev/1_QO/myQO/navidrome/scripts/vk-music-scanner/downloads/Asiye Saale/Asiye Saale - Yaşa menim halqım! (live).mp3",
      "downloaded_at": "2025-12-25T11:23:51.445706"
    },
    {
      "artist": "Asiye Saale",
      "title": "Kemançemniñ telleri (CT)",
      "db_artist": "Asiye Saale",
      "path": "/Volumes/T9/1_dev/1_QO/myQO/navidrome/scripts/vk-music-scanner/downloads/Asiye Saale/Asiye Saale - Kemançemniñ telleri (CT).mp3",
      "downloaded_at": "2025-12-25T11:23:54.344826"
    },
    {
      "artist": "Asiye Saale & Nariman Balich",
      "title": "Çalıquşu (Королёк птичка певчая) (Muzut.net)",
      "db_artist": "Asiye Saale",
      "path": "/Volumes/T9/1_dev/1_QO/myQO/navidrome/scripts/vk-music-scanner/downloads/Asiye Saale/Asiye Saale & Nariman Balich - Çalıquşu (Королёк птичка певчая) (Muzut.net).mp3",
      "downloaded_at": "2025-12-25T11:23:57.612016"
    },
    {
      "artist": "Asiye Saale",
      "title": "ЯР-ЯР-ЯР MP3",
      "db_artist": "Asiye Saale",
      "path": "/Volumes/T9/1_dev/1_QO/myQO/navidrome/scripts/vk-music-scanner/downloads/Asiye Saale/Asiye Saale - ЯР-ЯР-ЯР MP3.mp3",
      "downloaded_at": "2025-12-25T11:24:00.254162"
    },
    {
      "artist": "Asiye Saale, Elina Sosnovskaya, Safiye Denişayeva -",
      "title": "'Qırım - Vatanım",
      "db_artist": "Asiye Saale",
      "path": "/Volumes/T9/1_dev/1_QO/myQO/navidrome/scripts/vk-music-scanner/downloads/Asiye Saale/Asiye Saale, Elina Sosnovskaya, Safiye Denişayeva - - 'Qırım - Vatanım.mp3",
      "downloaded_at": "2025-12-25T11:24:04.054882"
    },
    {
      "artist": "Asiye Saale & Nariman Balich",
      "title": "alquu (Королёк птичка певчая)",
      "db_artist": "Asiye Saale",
      "path": "/Volumes/T9/1_dev/1_QO/myQO/navidrome/scripts/vk-music-scanner/downloads/Asiye Saale/Asiye Saale & Nariman Balich - alquu (Королёк птичка певчая).mp3",
      "downloaded_at": "2025-12-25T11:24:06.649045"
    },
    {
      "artist": "Asiye Saale",
      "title": "Girdim yarın bağçasına (instrumental)",
      "db_artist": "Asiye Saale",
      "path": "/Volumes/T9/1_dev/1_QO/myQO/navidrome/scripts/vk-music-scanner/downloads/Asiye Saale/Asiye Saale - Girdim yarın bağçasına (instrumental).mp3",
      "downloaded_at": "2025-12-25T11:24:08.805840"
    },
    {
      "artist": "Asiye Saale",
      "title": "Yaşa menim halqım (Live)",
      "db_artist": "Asiye Saale",
      "path": "/Volumes/T9/1_dev/1_QO/myQO/navidrome/scripts/vk-music-scanner/downloads/Asiye Saale/Asiye Saale - Yaşa menim halqım (Live).mp3",
      "downloaded_at": "2025-12-25T11:24:11.228900"
    },
    {
      "artist": "Balalar - Лиана Хабибуллина",
      "title": "Рамаҙан (Рамадан)",
      "db_artist": "Balalar",
      "path": "/Volumes/T9/1_dev/1_QO/myQO/navidrome/scripts/vk-music-scanner/downloads/Balalar/Balalar - Лиана Хабибуллина - Рамаҙан (Рамадан).mp3",
      "downloaded_at": "2025-12-25T11:24:13.680913"
    },
    {
      "artist": "Balalar",
      "title": "Armancik",
      "db_artist": "Balalar",
      "path": "/Volumes/T9/1_dev/1_QO/myQO/navidrome/scripts/vk-music-scanner/downloads/Balalar/Balalar - Armancik.mp3",
      "downloaded_at": "2025-12-25T11:24:15.974641"
    },
    {
      "artist": "Balalar",
      "title": "Qirimtatar aşları",
      "db_artist": "Balalar",
      "path": "/Volumes/T9/1_dev/1_QO/myQO/navidrome/scripts/vk-music-scanner/downloads/Balalar/Balalar - Qirimtatar aşları.mp3",
      "downloaded_at": "2025-12-25T11:25:33.291225"
    },
    {
      "artist": "Balalar",
      "title": "Elifbe",
      "db_artist": "Balalar",
      "path": "/Volumes/T9/1_dev/1_QO/myQO/navidrome/scripts/vk-music-scanner/downloads/Balalar/Balalar - Elifbe.mp3",
      "downloaded_at": "2025-12-25T11:28:05.473265"
    },
    {
      "artist": "Balalar",
      "title": "BIR OLAYIK BALALAR+",
      "db_artist": "Balalar",
      "path": "/Volumes/T9/1_dev/1_QO/myQO/navidrome/scripts/vk-music-scanner/downloads/Balalar/Balalar - BIR OLAYIK BALALAR+.mp3",
      "downloaded_at": "2025-12-25T11:29:23.110392"
    },
    {
      "artist": "Dj Bebek",
      "title": "Qamiş Qora qaytarması (Dj Bebek mix)",
      "db_artist": "DJ Bebek",
      "path": "/Volumes/T9/1_dev/1_QO/myQO/navidrome/scripts/vk-music-scanner/downloads/DJ Bebek/Dj Bebek - Qamiş Qora qaytarması (Dj Bebek mix).mp3",
      "downloaded_at": "2025-12-25T11:29:26.145195"
    },
    {
      "artist": "☾☆  dj bebek  & Зера Кенжикаева",
      "title": "Дегерменджи (produced by dj bebek mix 2011)",
      "db_artist": "DJ Bebek",
      "path": "/Volumes/T9/1_dev/1_QO/myQO/navidrome/scripts/vk-music-scanner/downloads/DJ Bebek/☾☆  dj bebek  & Зера Кенжикаева - Дегерменджи (produced by dj bebek mix 2011).mp3",
      "downloaded_at": "2025-12-25T11:29:29.495247"
    },
    {
      "artist": "AYA NAKAMURA, The Limba & Andro, Daddy Yankee, Kartashow, Мари Краймбрери, Conkarah feat. Shaggy, Нариман Балич & Dj Bebek",
      "title": "Mix by audio-joiner.com",
      "db_artist": "DJ Bebek",
      "path": "/Volumes/T9/1_dev/1_QO/myQO/navidrome/scripts/vk-music-scanner/downloads/DJ Bebek/AYA NAKAMURA, The Limba & Andro, Daddy Yankee, Kartashow, Мари Краймбрери, Conkarah feat. Shaggy, Нариман Балич & Dj Bebek - Mix by audio-joiner.com.mp3",
      "downloaded_at": "2025-12-25T11:29:32.522402"
    },
    {
      "artist": "dj bebek feat. Nial Bulenkova",
      "title": "Mademoiselle",
      "db_artist": "DJ Bebek",
      "path": "/Volumes/T9/1_dev/1_QO/myQO/navidrome/scripts/vk-music-scanner/downloads/DJ Bebek/dj bebek feat. Nial Bulenkova - Mademoiselle.mp3",
      "downloaded_at": "2025-12-25T11:29:35.357000"
    },
    {
      "artist": "Нариман Балич ве Dj Bebek",
      "title": "Догъгъан куню авасы",
      "db_artist": "DJ Bebek",
      "path": "/Volumes/T9/1_dev/1_QO/myQO/navidrome/scripts/vk-music-scanner/downloads/DJ Bebek/Нариман Балич ве Dj Bebek - Догъгъан куню авасы.mp3",
      "downloaded_at": "2025-12-25T11:29:39.195726"
    },
    {
      "artist": "Нариман Балич & Dj Bebek",
      "title": "Машаллах хайтармасы (Produced by Dj Bebek 2013)",
      "db_artist": "DJ Bebek",
      "path": "/Volumes/T9/1_dev/1_QO/myQO/navidrome/scripts/vk-music-scanner/downloads/DJ Bebek/Нариман Балич & Dj Bebek - Машаллах хайтармасы (Produced by Dj Bebek 2013).mp3",
      "downloaded_at": "2025-12-25T11:29:42.399296"
    },
    {
      "artist": "Nariman Balich & dj bebek",
      "title": "YAshlar Avasy (produced by dj bebek 2012)",
      "db_artist": "DJ Bebek",
      "path": "/Volumes/T9/1_dev/1_QO/myQO/navidrome/scripts/vk-music-scanner/downloads/DJ Bebek/Nariman Balich & dj bebek - YAshlar Avasy (produced by dj bebek 2012).mp3",
      "downloaded_at": "2025-12-25T11:29:46.284220"
    },
    {
      "artist": "Dj Bebek",
      "title": "Yosmam (Dj Bebek Mix)",
      "db_artist": "DJ Bebek",
      "path": "/Volumes/T9/1_dev/1_QO/myQO/navidrome/scripts/vk-music-scanner/downloads/DJ Bebek/Dj Bebek - Yosmam (Dj Bebek Mix).mp3",
      "downloaded_at": "2025-12-25T11:29:49.694881"
    },
    {
      "artist": "Dj Bebek",
      "title": "Тым-тым (Dj Bebek mix)",
      "db_artist": "DJ Bebek",
      "path": "/Volumes/T9/1_dev/1_QO/myQO/navidrome/scripts/vk-music-scanner/downloads/DJ Bebek/Dj Bebek - Тым-тым (Dj Bebek mix).mp3",
      "downloaded_at": "2025-12-25T11:29:58.458374"
    },
    {
      "artist": "Dj Aktiv feat. Dj Bebek",
      "title": "Balkan sound",
      "db_artist": "DJ Bebek",
      "path": "/Volumes/T9/1_dev/1_QO/myQO/navidrome/scripts/vk-music-scanner/downloads/DJ Bebek/Dj Aktiv feat. Dj Bebek - Balkan sound.mp3",
      "downloaded_at": "2025-12-25T11:30:02.415966"
    },
    {
      "artist": "[muzmo.ru] DJ Bebek",
      "title": "DJ BEBEK [muzmo.ru]",
      "db_artist": "DJ Bebek",
      "path": "/Volumes/T9/1_dev/1_QO/myQO/navidrome/scripts/vk-music-scanner/downloads/DJ Bebek/[muzmo.ru] DJ Bebek - DJ BEBEK [muzmo.ru].mp3",
      "downloaded_at": "2025-12-25T11:30:05.774997"
    },
    {
      "artist": "Dj Bebek vs DJ_OLiveR",
      "title": "kuchuk_ozen(REMIX)",
      "db_artist": "DJ Bebek",
      "path": "/Volumes/T9/1_dev/1_QO/myQO/navidrome/scripts/vk-music-scanner/downloads/DJ Bebek/Dj Bebek vs DJ_OLiveR - kuchuk_ozen(REMIX).mp3",
      "downloaded_at": "2025-12-25T11:30:09.837265"
    },
    {
      "artist": "DJ Bebek",
      "title": "Крым хайтарма",
      "db_artist": "DJ Bebek",
      "path": "/Volumes/T9/1_dev/1_QO/myQO/navidrome/scripts/vk-music-scanner/downloads/DJ Bebek/DJ Bebek - Крым хайтарма.mp3",
      "downloaded_at": "2025-12-25T11:30:14.242411"
    },
    {
      "artist": "dj bebek  feat Regina 2010 (6 лет)",
      "title": "(меннен берабер)",
      "db_artist": "DJ Bebek",
      "path": "/Volumes/T9/1_dev/1_QO/myQO/navidrome/scripts/vk-music-scanner/downloads/DJ Bebek/dj bebek  feat Regina 2010 (6 лет) - (меннен берабер).mp3",
      "downloaded_at": "2025-12-25T11:30:16.634140"
    },
    {
      "artist": "dj Bebek $ Alie Hadjabadinova",
      "title": "Aldattin",
      "db_artist": "DJ Bebek",
      "path": "/Volumes/T9/1_dev/1_QO/myQO/navidrome/scripts/vk-music-scanner/downloads/DJ Bebek/dj Bebek $ Alie Hadjabadinova - Aldattin.mp3",
      "downloaded_at": "2025-12-25T11:30:19.663941"
    },
    {
      "artist": "dj bebek & Зера Кенжикаева",
      "title": "Къызым,сени киме вереим (produced by dj bebek 2012)",
      "db_artist": "DJ Bebek",
      "path": "/Volumes/T9/1_dev/1_QO/myQO/navidrome/scripts/vk-music-scanner/downloads/DJ Bebek/dj bebek & Зера Кенжикаева - Къызым,сени киме вереим (produced by dj bebek 2012).mp3",
      "downloaded_at": "2025-12-25T11:30:23.195914"
    },
    {
      "artist": "Elnara Küçük ve DJ Bebek",
      "title": "Yüksek töpelere",
      "db_artist": "DJ Bebek",
      "path": "/Volumes/T9/1_dev/1_QO/myQO/navidrome/scripts/vk-music-scanner/downloads/DJ Bebek/Elnara Küçük ve DJ Bebek - Yüksek töpelere.mp3",
      "downloaded_at": "2025-12-25T11:30:27.422107"
    },
    {
      "artist": "Эльнара Кучук & dj bebek",
      "title": "Къызылчикълар (produced by dj bebek 2012)",
      "db_artist": "DJ Bebek",
      "path": "/Volumes/T9/1_dev/1_QO/myQO/navidrome/scripts/vk-music-scanner/downloads/DJ Bebek/Эльнара Кучук & dj bebek - Къызылчикълар (produced by dj bebek 2012).mp3",
      "downloaded_at": "2025-12-25T11:30:37.272848"
    },
    {
      "artist": "DJ Bebek  [http://musvkontakte.ru]",
      "title": "Kuchuk ozen (folk mix)  Для загрузки воспользуйтесь ссылкой - http://musvkontakte.ru/DJ Bebek.html",
      "db_artist": "DJ Bebek",
      "path": "/Volumes/T9/1_dev/1_QO/myQO/navidrome/scripts/vk-music-scanner/downloads/DJ Bebek/DJ Bebek  [http___musvkontakte.ru] - Kuchuk ozen (folk mix)  Для загрузки воспользуйтесь ссылкой - http___musvkontakte.ru_DJ Bebek.html.mp3",
      "downloaded_at": "2025-12-25T11:30:39.588644"
    },
    {
      "artist": "Регина & dj bebek",
      "title": "DOSTUM (produced by dj bebek 2012)",
      "db_artist": "DJ Bebek",
      "path": "/Volumes/T9/1_dev/1_QO/myQO/navidrome/scripts/vk-music-scanner/downloads/DJ Bebek/Регина & dj bebek - DOSTUM (produced by dj bebek 2012).mp3",
      "downloaded_at": "2025-12-25T11:30:42.874625"
    },
    {
      "artist": "KET-U and DJ Bebek feat. DJ SPACE ONE",
      "title": "Не Буду Одна 2012",
      "db_artist": "DJ Bebek",
      "path": "/Volumes/T9/1_dev/1_QO/myQO/navidrome/scripts/vk-music-scanner/downloads/DJ Bebek/KET-U and DJ Bebek feat. DJ SPACE ONE - Не Буду Одна 2012.mp3",
      "downloaded_at": "2025-12-25T11:30:45.232579"
    },
    {
      "artist": "Evelina & dj bebek",
      "title": "TUk TUk (Remix produced by dj bebek 2013)",
      "db_artist": "DJ Bebek",
      "path": "/Volumes/T9/1_dev/1_QO/myQO/navidrome/scripts/vk-music-scanner/downloads/DJ Bebek/Evelina & dj bebek - TUk TUk (Remix produced by dj bebek 2013).mp3",
      "downloaded_at": "2025-12-25T11:30:48.137537"
    },
    {
      "artist": "Dilâra Mahmudova & Feride Ablâzova",
      "title": "Vatanim Qırım",
      "db_artist": "Dilâra Mahmudova",
      "path": "/Volumes/T9/1_dev/1_QO/myQO/navidrome/scripts/vk-music-scanner/downloads/Dilâra Mahmudova/Dilâra Mahmudova & Feride Ablâzova - Vatanim Qırım.mp3",
      "downloaded_at": "2025-12-25T11:30:51.617199"
    },
    {
      "artist": "Dilâver Osmanov ve Qırım",
      "title": "Ayşe hanım",
      "db_artist": "Dilâver Osmanov",
      "path": "/Volumes/T9/1_dev/1_QO/myQO/navidrome/scripts/vk-music-scanner/downloads/Dilâver Osmanov/Dilâver Osmanov ve Qırım - Ayşe hanım.mp3",
      "downloaded_at": "2025-12-25T11:30:55.395508"
    },
    {
      "artist": "Osmanov",
      "title": "Бомбита",
      "db_artist": "Dilâver Osmanov",
      "path": "/Volumes/T9/1_dev/1_QO/myQO/navidrome/scripts/vk-music-scanner/downloads/Dilâver Osmanov/Osmanov - Бомбита.mp3",
      "downloaded_at": "2025-12-25T11:30:58.171972"
    },
    {
      "artist": "Osmanov",
      "title": "Магия",
      "db_artist": "Dilâver Osmanov",
      "path": "/Volumes/T9/1_dev/1_QO/myQO/navidrome/scripts/vk-music-scanner/downloads/Dilâver Osmanov/Osmanov - Магия.mp3",
      "downloaded_at": "2025-12-25T11:31:02.491871"
    },
    {
      "artist": "Dilaver Osmanov",
      "title": "Mýna selamaleyküm",
      "db_artist": "Dilâver Osmanov",
      "path": "/Volumes/T9/1_dev/1_QO/myQO/navidrome/scripts/vk-music-scanner/downloads/Dilâver Osmanov/Dilaver Osmanov - Mýna selamaleyküm.mp3",
      "downloaded_at": "2025-12-25T11:31:05.026523"
    },
    {
      "artist": "Dilaver Osmanov",
      "title": "Acı Molla, Qurt Molla",
      "db_artist": "Dilâver Osmanov",
      "path": "/Volumes/T9/1_dev/1_QO/myQO/navidrome/scripts/vk-music-scanner/downloads/Dilâver Osmanov/Dilaver Osmanov - Acı Molla, Qurt Molla.mp3",
      "downloaded_at": "2025-12-25T11:31:07.292769"
    },
    {
      "artist": "Osmanov",
      "title": "Взорви",
      "db_artist": "Dilâver Osmanov",
      "path": "/Volumes/T9/1_dev/1_QO/myQO/navidrome/scripts/vk-music-scanner/downloads/Dilâver Osmanov/Osmanov - Взорви.mp3",
      "downloaded_at": "2025-12-25T11:31:10.647048"
    },
    {
      "artist": "OsMan",
      "title": "Disaster",
      "db_artist": "Dilâver Osmanov",
      "path": "/Volumes/T9/1_dev/1_QO/myQO/navidrome/scripts/vk-music-scanner/downloads/Dilâver Osmanov/OsMan - Disaster.mp3",
      "downloaded_at": "2025-12-25T11:31:15.971282"
    },
    {
      "artist": "Dilâver Osmanov",
      "title": "Aqtaban",
      "db_artist": "Dilâver Osmanov",
      "path": "/Volumes/T9/1_dev/1_QO/myQO/navidrome/scripts/vk-music-scanner/downloads/Dilâver Osmanov/Dilâver Osmanov - Aqtaban.mp3",
      "downloaded_at": "2025-12-25T11:31:18.307015"
    },
    {
      "artist": "Nariman Balich, Elzara Batalova",
      "title": "Kele Bahar",
      "db_artist": "Elzara Batalova",
      "path": "/Volumes/T9/1_dev/1_QO/myQO/navidrome/scripts/vk-music-scanner/downloads/Elzara Batalova/Nariman Balich, Elzara Batalova - Kele Bahar.mp3",
      "downloaded_at": "2025-12-25T11:31:26.119424"
    },
    {
      "artist": "Destan ve Elzara Batalova (Meydan FM 10 yil)",
      "title": "Осман паша.",
      "db_artist": "Elzara Batalova",
      "path": "/Volumes/T9/1_dev/1_QO/myQO/navidrome/scripts/vk-music-scanner/downloads/Elzara Batalova/Destan ve Elzara Batalova (Meydan FM 10 yil) - Осман паша.mp3",
      "downloaded_at": "2025-12-25T11:31:29.673785"
    },
    {
      "artist": "Elzara Batalova",
      "title": "Новий день (CT)",
      "db_artist": "Elzara Batalova",
      "path": "/Volumes/T9/1_dev/1_QO/myQO/navidrome/scripts/vk-music-scanner/downloads/Elzara Batalova/Elzara Batalova - Новий день (CT).mp3",
      "downloaded_at": "2025-12-25T11:31:32.464549"
    },
    {
      "artist": "Elzara Batalova",
      "title": "Kele baar (N I Y E T)",
      "db_artist": "Elzara Batalova",
      "path": "/Volumes/T9/1_dev/1_QO/myQO/navidrome/scripts/vk-music-scanner/downloads/Elzara Batalova/Elzara Batalova - Kele baar (N I Y E T).mp3",
      "downloaded_at": "2025-12-25T11:31:34.980401"
    },
    {
      "artist": "Elzara Batalova",
      "title": "Ey Guzel Qirim! (live)",
      "db_artist": "Elzara Batalova",
      "path": "/Volumes/T9/1_dev/1_QO/myQO/navidrome/scripts/vk-music-scanner/downloads/Elzara Batalova/Elzara Batalova - Ey Guzel Qirim! (live).mp3",
      "downloaded_at": "2025-12-25T11:31:37.826477"
    },
    {
      "artist": "Elzara Batalova",
      "title": "Qarşıdan fener kelir (CT)",
      "db_artist": "Elzara Batalova",
      "path": "/Volumes/T9/1_dev/1_QO/myQO/navidrome/scripts/vk-music-scanner/downloads/Elzara Batalova/Elzara Batalova - Qarşıdan fener kelir (CT).mp3",
      "downloaded_at": "2025-12-25T11:31:39.835547"
    },
    {
      "artist": "Elzara Batalova. Guzel Qirim. 28.03.2009.",
      "title": "Elzara Batalova. Guzel Qirim. - YouTube",
      "db_artist": "Elzara Batalova",
      "path": "/Volumes/T9/1_dev/1_QO/myQO/navidrome/scripts/vk-music-scanner/downloads/Elzara Batalova/Elzara Batalova. Guzel Qirim. 28.03.2009 - Elzara Batalova. Guzel Qirim. - YouTube.mp3",
      "downloaded_at": "2025-12-25T11:31:42.525078"
    },
    {
      "artist": "Emine Mustafayeva, Enver Karimov, Vardui Dilanyan, Mihail Şlık",
      "title": "Qırım yaşlarınıñ gimni (Гімн молоді Криму/Гимн молодежи Крыма)",
      "db_artist": "Emine Mustafayeva",
      "path": "/Volumes/T9/1_dev/1_QO/myQO/navidrome/scripts/vk-music-scanner/downloads/Emine Mustafayeva/Emine Mustafayeva, Enver Karimov, Vardui Dilanyan, Mihail Şlık - Qırım yaşlarınıñ gimni (Гімн молоді Криму_Гимн молодежи Крыма).mp3",
      "downloaded_at": "2025-12-25T11:31:45.057037"
    },
    {
      "artist": "Emine Mustafayeva",
      "title": "ASAN (HIT!!!)",
      "db_artist": "Emine Mustafayeva",
      "path": "/Volumes/T9/1_dev/1_QO/myQO/navidrome/scripts/vk-music-scanner/downloads/Emine Mustafayeva/Emine Mustafayeva - ASAN (HIT!!!).mp3",
      "downloaded_at": "2025-12-25T11:31:47.312273"
    },
    {
      "artist": "Filis - Emine Mustafayeva-Samedin",
      "title": "Меным ватаным",
      "db_artist": "Emine Mustafayeva",
      "path": "/Volumes/T9/1_dev/1_QO/myQO/navidrome/scripts/vk-music-scanner/downloads/Emine Mustafayeva/Filis - Emine Mustafayeva-Samedin - Меным ватаным.mp3",
      "downloaded_at": "2025-12-25T11:31:54.624039"
    },
    {
      "artist": "Emine Mustafayeva",
      "title": "Gögercin (CT)",
      "db_artist": "Emine Mustafayeva",
      "path": "/Volumes/T9/1_dev/1_QO/myQO/navidrome/scripts/vk-music-scanner/downloads/Emine Mustafayeva/Emine Mustafayeva - Gögercin (CT).mp3",
      "downloaded_at": "2025-12-25T11:33:12.022296"
    },
    {
      "artist": "Emine Mustafayeva ve Server Kakura",
      "title": "Üç gögercin (Live | Piano version)",
      "db_artist": "Emine Mustafayeva",
      "path": "/Volumes/T9/1_dev/1_QO/myQO/navidrome/scripts/vk-music-scanner/downloads/Emine Mustafayeva/Emine Mustafayeva ve Server Kakura - Üç gögercin (Live _ Piano version).mp3",
      "downloaded_at": "2025-12-25T11:33:14.772276"
    },
    {
      "artist": "Emine Mustafayeva",
      "title": "Dostum (Crimean)",
      "db_artist": "Emine Mustafayeva",
      "path": "/Volumes/T9/1_dev/1_QO/myQO/navidrome/scripts/vk-music-scanner/downloads/Emine Mustafayeva/Emine Mustafayeva - Dostum (Crimean).mp3",
      "downloaded_at": "2025-12-25T11:33:17.548976"
    },
    {
      "artist": "Emine Mustafayeva",
      "title": "Gögercin (live)",
      "db_artist": "Emine Mustafayeva",
      "path": "/Volumes/T9/1_dev/1_QO/myQO/navidrome/scripts/vk-music-scanner/downloads/Emine Mustafayeva/Emine Mustafayeva - Gögercin (live).mp3",
      "downloaded_at": "2025-12-25T11:33:19.847782"
    },
    {
      "artist": "Эмине Мустафаева - Emine Mustafayeva",
      "title": "Сойлемее лаф арайым",
      "db_artist": "Emine Mustafayeva",
      "path": "/Volumes/T9/1_dev/1_QO/myQO/navidrome/scripts/vk-music-scanner/downloads/Emine Mustafayeva/Эмине Мустафаева - Emine Mustafayeva - Сойлемее лаф арайым.mp3",
      "downloaded_at": "2025-12-25T11:33:22.472666"
    },
    {
      "artist": "Env",
      "title": "Enn",
      "db_artist": "Enver İzmaylov",
      "path": "/Volumes/T9/1_dev/1_QO/myQO/navidrome/scripts/vk-music-scanner/downloads/Enver İzmaylov/Env - Enn.mp3",
      "downloaded_at": "2025-12-25T11:33:25.900029"
    },
    {
      "artist": "Fevzi Bilalov",
      "title": "Badem terek (CT)",
      "db_artist": "Fevzi Bilâlov",
      "path": "/Volumes/T9/1_dev/1_QO/myQO/navidrome/scripts/vk-music-scanner/downloads/Fevzi Bilâlov/Fevzi Bilalov - Badem terek (CT).mp3",
      "downloaded_at": "2025-12-25T11:33:27.946948"
    },
    {
      "artist": "Zahide Gunesh",
      "title": "Sensizem",
      "db_artist": "Güneş",
      "path": "/Volumes/T9/1_dev/1_QO/myQO/navidrome/scripts/vk-music-scanner/downloads/Güneş/Zahide Gunesh - Sensizem.mp3",
      "downloaded_at": "2025-12-25T11:33:30.355377"
    },
    {
      "artist": "Sertan Gunes feat. D'layna",
      "title": "Dance All Night",
      "db_artist": "Güneş",
      "path": "/Volumes/T9/1_dev/1_QO/myQO/navidrome/scripts/vk-music-scanner/downloads/Güneş/Sertan Gunes feat. D'layna - Dance All Night.mp3",
      "downloaded_at": "2025-12-25T11:33:33.167261"
    },
    {
      "artist": "İbrahim Güzelses",
      "title": "Güzeller",
      "db_artist": "Güzel",
      "path": "/Volumes/T9/1_dev/1_QO/myQO/navidrome/scripts/vk-music-scanner/downloads/Güzel/İbrahim Güzelses - Güzeller.mp3",
      "downloaded_at": "2025-12-25T11:33:36.062058"
    },
    {
      "artist": "Halq icrası",
      "title": "Qırım yırları",
      "db_artist": "Halq icrası",
      "path": "/Volumes/T9/1_dev/1_QO/myQO/navidrome/scripts/vk-music-scanner/downloads/Halq icrası/Halq icrası - Qırım yırları.mp3",
      "downloaded_at": "2025-12-25T11:33:40.187244"
    },
    {
      "artist": "Halq icrası",
      "title": "Ey güzel Qırım (instrumental)",
      "db_artist": "Halq icrası",
      "path": "/Volumes/T9/1_dev/1_QO/myQO/navidrome/scripts/vk-music-scanner/downloads/Halq icrası/Halq icrası - Ey güzel Qırım (instrumental).mp3",
      "downloaded_at": "2025-12-25T11:33:42.585383"
    },
    {
      "artist": "Halq icrası",
      "title": "Tatar barmı dep kim soray (live)",
      "db_artist": "Halq icrası",
      "path": "/Volumes/T9/1_dev/1_QO/myQO/navidrome/scripts/vk-music-scanner/downloads/Halq icrası/Halq icrası - Tatar barmı dep kim soray (live).mp3",
      "downloaded_at": "2025-12-25T11:33:45.060854"
    },
    {
      "artist": "Jamala",
      "title": "Krila",
      "db_artist": "Jamala",
      "path": "/Volumes/T9/1_dev/1_QO/myQO/navidrome/scripts/vk-music-scanner/downloads/Jamala/Jamala - Krila.mp3",
      "downloaded_at": "2025-12-25T11:33:53.370836"
    },
    {
      "artist": "Jamala",
      "title": "Шлях додому.mp3",
      "db_artist": "Jamala",
      "path": "/Volumes/T9/1_dev/1_QO/myQO/navidrome/scripts/vk-music-scanner/downloads/Jamala/Jamala - Шлях додому.mp3.mp3",
      "downloaded_at": "2025-12-25T11:34:02.544360"
    },
    {
      "artist": "Jamala",
      "title": "1944 (DJ Rzayev Remix) https://vk.com/ua.club.music Українська електронна музика Українська музика",
      "db_artist": "Jamala",
      "path": "/Volumes/T9/1_dev/1_QO/myQO/navidrome/scripts/vk-music-scanner/downloads/Jamala/Jamala - 1944 (DJ Rzayev Remix) https___vk.com_ua.club.music Українська електронна музика Українська музика.mp3",
      "downloaded_at": "2025-12-25T11:34:05.301252"
    },
    {
      "artist": "Jamala",
      "title": "Я люблю тебя (All or Nothing '2013)",
      "db_artist": "Jamala",
      "path": "/Volumes/T9/1_dev/1_QO/myQO/navidrome/scripts/vk-music-scanner/downloads/Jamala/Jamala - Я люблю тебя (All or Nothing '2013).mp3",
      "downloaded_at": "2025-12-25T11:34:08.545546"
    },
    {
      "artist": "1146.Jamala(Джамала)",
      "title": "Обещание (https://vk.com/skromno)",
      "db_artist": "Jamala",
      "path": "/Volumes/T9/1_dev/1_QO/myQO/navidrome/scripts/vk-music-scanner/downloads/Jamala/1146.Jamala(Джамала) - Обещание (https___vk.com_skromno).mp3",
      "downloaded_at": "2025-12-25T11:34:16.354909"
    },
    {
      "artist": "Jamala",
      "title": "Сумую",
      "db_artist": "Jamala",
      "path": "/Volumes/T9/1_dev/1_QO/myQO/navidrome/scripts/vk-music-scanner/downloads/Jamala/Jamala - Сумую.mp3",
      "downloaded_at": "2025-12-25T11:34:19.144868"
    },
    {
      "artist": "Jamala (Джамала) & Pianoбой",
      "title": "Эндорфины | #vqMusic ོ",
      "db_artist": "Jamala",
      "path": "/Volumes/T9/1_dev/1_QO/myQO/navidrome/scripts/vk-music-scanner/downloads/Jamala/Jamala (Джамала) & Pianoбой - Эндорфины _ #vqMusic ོ.mp3",
      "downloaded_at": "2025-12-25T11:34:26.778052"
    },
    {
      "artist": "Jamala",
      "title": "It's Me Jamala (original album version)",
      "db_artist": "Jamala",
      "path": "/Volumes/T9/1_dev/1_QO/myQO/navidrome/scripts/vk-music-scanner/downloads/Jamala/Jamala - It's Me Jamala (original album version).mp3",
      "downloaded_at": "2025-12-25T11:34:29.333673"
    },
    {
      "artist": "Jamala (Джамала)",
      "title": "Watch Over Me",
      "db_artist": "Jamala",
      "path": "/Volumes/T9/1_dev/1_QO/myQO/navidrome/scripts/vk-music-scanner/downloads/Jamala/Jamala (Джамала) - Watch Over Me.mp3",
      "downloaded_at": "2025-12-25T11:34:32.386248"
    },
    {
      "artist": "Jamala (Джамала)",
      "title": "1944 (Евровидение 2016 Украина) (Sefon.me)",
      "db_artist": "Jamala",
      "path": "/Volumes/T9/1_dev/1_QO/myQO/navidrome/scripts/vk-music-scanner/downloads/Jamala/Jamala (Джамала) - 1944 (Евровидение 2016 Украина) (Sefon.me).mp3",
      "downloaded_at": "2025-12-25T11:34:36.544049"
    },
    {
      "artist": "JAMALA",
      "title": "1944 (The Faino Radio Edit)",
      "db_artist": "Jamala",
      "path": "/Volumes/T9/1_dev/1_QO/myQO/navidrome/scripts/vk-music-scanner/downloads/Jamala/JAMALA - 1944 (The Faino Radio Edit).mp3",
      "downloaded_at": "2025-12-25T11:34:40.319431"
    },
    {
      "artist": "Jamala",
      "title": "How To Explain (All or Nothing '2013)",
      "db_artist": "Jamala",
      "path": "/Volumes/T9/1_dev/1_QO/myQO/navidrome/scripts/vk-music-scanner/downloads/Jamala/Jamala - How To Explain (All or Nothing '2013).mp3",
      "downloaded_at": "2025-12-25T11:34:43.084855"
    },
    {
      "artist": "Jamala",
      "title": "History Repeating (For Every Heart`2011)",
      "db_artist": "Jamala",
      "path": "/Volumes/T9/1_dev/1_QO/myQO/navidrome/scripts/vk-music-scanner/downloads/Jamala/Jamala - History Repeating (For Every Heart`2011).mp3",
      "downloaded_at": "2025-12-25T11:34:45.464921"
    },
    {
      "artist": "Jamala",
      "title": "YOSMAM",
      "db_artist": "Jamala",
      "path": "/Volumes/T9/1_dev/1_QO/myQO/navidrome/scripts/vk-music-scanner/downloads/Jamala/Jamala - YOSMAM.mp3",
      "downloaded_at": "2025-12-25T11:34:48.757270"
    },
    {
      "artist": "Jamala (Джамала)",
      "title": "У Осени Твои Глаза",
      "db_artist": "Jamala",
      "path": "/Volumes/T9/1_dev/1_QO/myQO/navidrome/scripts/vk-music-scanner/downloads/Jamala/Jamala (Джамала) - У Осени Твои Глаза.mp3",
      "downloaded_at": "2025-12-25T11:34:56.127608"
    },
    {
      "artist": "Leniye İzmaylova",
      "title": "Haytarma (Crimean)",
      "db_artist": "Leniye İzmaylova",
      "path": "/Volumes/T9/1_dev/1_QO/myQO/navidrome/scripts/vk-music-scanner/downloads/Leniye İzmaylova/Leniye İzmaylova - Haytarma (Crimean).mp3",
      "downloaded_at": "2025-12-25T11:34:58.509487"
    },
    {
      "artist": "Leniye Izmaylova&BEBEK",
      "title": "Без названия",
      "db_artist": "Leniye İzmaylova",
      "path": "/Volumes/T9/1_dev/1_QO/myQO/navidrome/scripts/vk-music-scanner/downloads/Leniye İzmaylova/Leniye Izmaylova&BEBEK - Без названия.mp3",
      "downloaded_at": "2025-12-25T11:35:01.554840"
    },
    {
      "artist": "leniye izmaylova",
      "title": "qirim",
      "db_artist": "Leniye İzmaylova",
      "path": "/Volumes/T9/1_dev/1_QO/myQO/navidrome/scripts/vk-music-scanner/downloads/Leniye İzmaylova/leniye izmaylova - qirim.mp3",
      "downloaded_at": "2025-12-25T11:35:04.512467"
    },
    {
      "artist": "Leniye İzmaylova",
      "title": "Er vaqıt (CT)",
      "db_artist": "Leniye İzmaylova",
      "path": "/Volumes/T9/1_dev/1_QO/myQO/navidrome/scripts/vk-music-scanner/downloads/Leniye İzmaylova/Leniye İzmaylova - Er vaqıt (CT).mp3",
      "downloaded_at": "2025-12-25T11:35:07.019528"
    },
    {
      "artist": "Asiye Saale, Nariman Balich",
      "title": "Ay, çalaşım",
      "db_artist": "Nariman Baliç",
      "path": "/Volumes/T9/1_dev/1_QO/myQO/navidrome/scripts/vk-music-scanner/downloads/Nariman Baliç/Asiye Saale, Nariman Balich - Ay, çalaşım.mp3",
      "downloaded_at": "2025-12-25T11:35:13.098841"
    },
    {
      "artist": "Reyan Kadırova, Nariman Balich",
      "title": "Qaydasın",
      "db_artist": "Nariman Baliç",
      "path": "/Volumes/T9/1_dev/1_QO/myQO/navidrome/scripts/vk-music-scanner/downloads/Nariman Baliç/Reyan Kadırova, Nariman Balich - Qaydasın.mp3",
      "downloaded_at": "2025-12-25T11:35:16.134270"
    },
    {
      "artist": "Reyan Kadırova, Nariman Balich",
      "title": "Yüregimde Ol",
      "db_artist": "Nariman Baliç",
      "path": "/Volumes/T9/1_dev/1_QO/myQO/navidrome/scripts/vk-music-scanner/downloads/Nariman Baliç/Reyan Kadırova, Nariman Balich - Yüregimde Ol.mp3",
      "downloaded_at": "2025-12-25T11:35:23.351046"
    },
    {
      "artist": "Reyan Kadırova, Nariman Balich",
      "title": "Made in Qırım Tatar (Remix)",
      "db_artist": "Nariman Baliç",
      "path": "/Volumes/T9/1_dev/1_QO/myQO/navidrome/scripts/vk-music-scanner/downloads/Nariman Baliç/Reyan Kadırova, Nariman Balich - Made in Qırım Tatar (Remix).mp3",
      "downloaded_at": "2025-12-25T11:35:26.420705"
    },
    {
      "artist": "ASIE SAALE & NARIMAN BALICH",
      "title": "\"SEVGINE INAN\"",
      "db_artist": "Nariman Baliç",
      "path": "/Volumes/T9/1_dev/1_QO/myQO/navidrome/scripts/vk-music-scanner/downloads/Nariman Baliç/ASIE SAALE & NARIMAN BALICH - _SEVGINE INAN_.mp3",
      "downloaded_at": "2025-12-25T11:35:29.495647"
    },
    {
      "artist": "Asiye Saale & Nariman Balich",
      "title": "Mesafe",
      "db_artist": "Nariman Baliç",
      "path": "/Volumes/T9/1_dev/1_QO/myQO/navidrome/scripts/vk-music-scanner/downloads/Nariman Baliç/Asiye Saale & Nariman Balich - Mesafe.mp3",
      "downloaded_at": "2025-12-25T11:35:33.270515"
    },
    {
      "artist": "Nariman Baliç",
      "title": "Sürgünlük",
      "db_artist": "Nariman Baliç",
      "path": "/Volumes/T9/1_dev/1_QO/myQO/navidrome/scripts/vk-music-scanner/downloads/Nariman Baliç/Nariman Baliç - Sürgünlük.mp3",
      "downloaded_at": "2025-12-25T11:35:36.210617"
    },
    {
      "artist": "Asiye Saale, Nariman Balich",
      "title": "Sevemiz",
      "db_artist": "Nariman Baliç",
      "path": "/Volumes/T9/1_dev/1_QO/myQO/navidrome/scripts/vk-music-scanner/downloads/Nariman Baliç/Asiye Saale, Nariman Balich - Sevemiz.mp3",
      "downloaded_at": "2025-12-25T11:35:43.153505"
    },
    {
      "artist": "DJ Bebek  Nariman Baliç ve",
      "title": "Party",
      "db_artist": "Nariman Baliç",
      "path": "/Volumes/T9/1_dev/1_QO/myQO/navidrome/scripts/vk-music-scanner/downloads/Nariman Baliç/DJ Bebek  Nariman Baliç ve - Party.mp3",
      "downloaded_at": "2025-12-25T11:35:50.530121"
    },
    {
      "artist": "Nariman Balich",
      "title": "Qırımda Yaşa (feat. Asiye Saale)",
      "db_artist": "Nariman Baliç",
      "path": "/Volumes/T9/1_dev/1_QO/myQO/navidrome/scripts/vk-music-scanner/downloads/Nariman Baliç/Nariman Balich - Qırımda Yaşa (feat. Asiye Saale).mp3",
      "downloaded_at": "2025-12-25T11:35:57.734536"
    },
    {
      "artist": "Nariman Balich",
      "title": "Çalıquşu (feat. Asiye Saale)",
      "db_artist": "Nariman Baliç",
      "path": "/Volumes/T9/1_dev/1_QO/myQO/navidrome/scripts/vk-music-scanner/downloads/Nariman Baliç/Nariman Balich - Çalıquşu (feat. Asiye Saale).mp3",
      "downloaded_at": "2025-12-25T11:36:04.422212"
    },
    {
      "artist": "Nariman Balich",
      "title": "Aqay Club Avası",
      "db_artist": "Nariman Baliç",
      "path": "/Volumes/T9/1_dev/1_QO/myQO/navidrome/scripts/vk-music-scanner/downloads/Nariman Baliç/Nariman Balich - Aqay Club Avası.mp3",
      "downloaded_at": "2025-12-25T11:36:08.010324"
    },
    {
      "artist": "REYAN & NARIMAN BALICH & JAMDEEN",
      "title": "MADE IN QIRIMTATAR",
      "db_artist": "Nariman Baliç",
      "path": "/Volumes/T9/1_dev/1_QO/myQO/navidrome/scripts/vk-music-scanner/downloads/Nariman Baliç/REYAN & NARIMAN BALICH & JAMDEEN - MADE IN QIRIMTATAR.mp3",
      "downloaded_at": "2025-12-25T11:37:28.996024"
    },
    {
      "artist": "Reyan Kadırova, Nariman Balich",
      "title": "Sen",
      "db_artist": "Nariman Baliç",
      "path": "/Volumes/T9/1_dev/1_QO/myQO/navidrome/scripts/vk-music-scanner/downloads/Nariman Baliç/Reyan Kadırova, Nariman Balich - Sen.mp3",
      "downloaded_at": "2025-12-25T11:37:35.901015"
    },
    {
      "artist": "Asiye Saale & Nariman Balich",
      "title": "Quşlar Avada",
      "db_artist": "Nariman Baliç",
      "path": "/Volumes/T9/1_dev/1_QO/myQO/navidrome/scripts/vk-music-scanner/downloads/Nariman Baliç/Asiye Saale & Nariman Balich - Quşlar Avada.mp3",
      "downloaded_at": "2025-12-25T11:37:42.971848"
    },
    {
      "artist": "Qarasuv",
      "title": "Asabay qaday",
      "db_artist": "Qarasuv",
      "path": "/Volumes/T9/1_dev/1_QO/myQO/navidrome/scripts/vk-music-scanner/downloads/Qarasuv/Qarasuv - Asabay qaday.mp3",
      "downloaded_at": "2025-12-25T11:37:45.810858"
    },
    {
      "artist": "Qarasuv",
      "title": "Azbarında quyusu var",
      "db_artist": "Qarasuv",
      "path": "/Volumes/T9/1_dev/1_QO/myQO/navidrome/scripts/vk-music-scanner/downloads/Qarasuv/Qarasuv - Azbarında quyusu var.mp3",
      "downloaded_at": "2025-12-25T11:37:48.351778"
    },
    {
      "artist": "Qarasuv taqimi",
      "title": "Seni kordikche",
      "db_artist": "Qarasuv",
      "path": "/Volumes/T9/1_dev/1_QO/myQO/navidrome/scripts/vk-music-scanner/downloads/Qarasuv/Qarasuv taqimi - Seni kordikche.mp3",
      "downloaded_at": "2025-12-25T11:37:51.219042"
    },
    {
      "artist": "Qarasuv taqimi",
      "title": "Djanay",
      "db_artist": "Qarasuv",
      "path": "/Volumes/T9/1_dev/1_QO/myQO/navidrome/scripts/vk-music-scanner/downloads/Qarasuv/Qarasuv taqimi - Djanay.mp3",
      "downloaded_at": "2025-12-25T11:37:53.504085"
    },
    {
      "artist": "Qarasuv taqimi",
      "title": "Qara qiz maqami",
      "db_artist": "Qarasuv",
      "path": "/Volumes/T9/1_dev/1_QO/myQO/navidrome/scripts/vk-music-scanner/downloads/Qarasuv/Qarasuv taqimi - Qara qiz maqami.mp3",
      "downloaded_at": "2025-12-25T11:37:56.921289"
    },
    {
      "artist": "Qarasuv taqimi",
      "title": "Aydi Canim",
      "db_artist": "Qarasuv",
      "path": "/Volumes/T9/1_dev/1_QO/myQO/navidrome/scripts/vk-music-scanner/downloads/Qarasuv/Qarasuv taqimi - Aydi Canim.mp3",
      "downloaded_at": "2025-12-25T11:37:59.671795"
    },
    {
      "artist": "Qarasuv",
      "title": "Papirosım",
      "db_artist": "Qarasuv",
      "path": "/Volumes/T9/1_dev/1_QO/myQO/navidrome/scripts/vk-music-scanner/downloads/Qarasuv/Qarasuv - Papirosım.mp3",
      "downloaded_at": "2025-12-25T11:38:02.109883"
    },
    {
      "artist": "Qırım",
      "title": "Emir Celâl ve haytarma (Фильм Хайтарма)",
      "db_artist": "Qırım",
      "path": "/Volumes/T9/1_dev/1_QO/myQO/navidrome/scripts/vk-music-scanner/downloads/Qırım/Qırım - Emir Celâl ve haytarma (Фильм Хайтарма).mp3",
      "downloaded_at": "2025-12-25T11:38:04.527733"
    },
    {
      "artist": "Qırım",
      "title": "Adalet",
      "db_artist": "Qırım",
      "path": "/Volumes/T9/1_dev/1_QO/myQO/navidrome/scripts/vk-music-scanner/downloads/Qırım/Qırım - Adalet.mp3",
      "downloaded_at": "2025-12-25T11:38:07.155842"
    },
    {
      "artist": "Reyana Kadırova",
      "title": "Dağlarnıñ yolları (СТ)",
      "db_artist": "Reyana Kadırova",
      "path": "/Volumes/T9/1_dev/1_QO/myQO/navidrome/scripts/vk-music-scanner/downloads/Reyana Kadırova/Reyana Kadırova - Dağlarnıñ yolları (СТ).mp3",
      "downloaded_at": "2025-12-25T11:38:09.724037"
    },
    {
      "artist": "Reyana Kadırova ve ATR ansambli",
      "title": "Çiğdem der ki (Aşık Veysel)",
      "db_artist": "Reyana Kadırova",
      "path": "/Volumes/T9/1_dev/1_QO/myQO/navidrome/scripts/vk-music-scanner/downloads/Reyana Kadırova/Reyana Kadırova ve ATR ansambli - Çiğdem der ki (Aşık Veysel).mp3",
      "downloaded_at": "2025-12-25T11:38:12.495009"
    },
    {
      "artist": "Reyana Kadırova",
      "title": "Arnautlar Eker Baqla",
      "db_artist": "Reyana Kadırova",
      "path": "/Volumes/T9/1_dev/1_QO/myQO/navidrome/scripts/vk-music-scanner/downloads/Reyana Kadırova/Reyana Kadırova - Arnautlar Eker Baqla.mp3",
      "downloaded_at": "2025-12-25T11:38:14.701275"
    },
    {
      "artist": "Rustem Memetov",
      "title": "Bulutlar",
      "db_artist": "Rustem Memetov",
      "path": "/Volumes/T9/1_dev/1_QO/myQO/navidrome/scripts/vk-music-scanner/downloads/Rustem Memetov/Rustem Memetov - Bulutlar.mp3",
      "downloaded_at": "2025-12-25T11:39:32.295181"
    },
    {
      "artist": "Rustem Memetov",
      "title": "acma da yarem",
      "db_artist": "Rustem Memetov",
      "path": "/Volumes/T9/1_dev/1_QO/myQO/navidrome/scripts/vk-music-scanner/downloads/Rustem Memetov/Rustem Memetov - acma da yarem.mp3",
      "downloaded_at": "2025-12-25T11:39:35.969627"
    },
    {
      "artist": "Rustem Memetov",
      "title": "Badem Terek (одна из моих любимых Крымско - татарских песен)",
      "db_artist": "Rustem Memetov",
      "path": "/Volumes/T9/1_dev/1_QO/myQO/navidrome/scripts/vk-music-scanner/downloads/Rustem Memetov/Rustem Memetov - Badem Terek (одна из моих любимых Крымско - татарских песен).mp3",
      "downloaded_at": "2025-12-25T11:39:39.230169"
    },
    {
      "artist": "Rustem Memetov",
      "title": "Halq yırı",
      "db_artist": "Rustem Memetov",
      "path": "/Volumes/T9/1_dev/1_QO/myQO/navidrome/scripts/vk-music-scanner/downloads/Rustem Memetov/Rustem Memetov - Halq yırı.mp3",
      "downloaded_at": "2025-12-25T11:39:41.686443"
    },
    {
      "artist": "Rustem Memetov - Server Kakura",
      "title": "VATANIM QIRIM,MILLETIM QIRIM",
      "db_artist": "Rustem Memetov",
      "path": "/Volumes/T9/1_dev/1_QO/myQO/navidrome/scripts/vk-music-scanner/downloads/Rustem Memetov/Rustem Memetov - Server Kakura - VATANIM QIRIM,MILLETIM QIRIM.mp3",
      "downloaded_at": "2025-12-25T11:39:45.498600"
    },
    {
      "artist": "Rustem Memetov",
      "title": "Milletim QIRIM",
      "db_artist": "Rustem Memetov",
      "path": "/Volumes/T9/1_dev/1_QO/myQO/navidrome/scripts/vk-music-scanner/downloads/Rustem Memetov/Rustem Memetov - Milletim QIRIM.mp3",
      "downloaded_at": "2025-12-25T11:39:47.730604"
    },
    {
      "artist": "Sabriye Erecepova",
      "title": "Pamuqçı",
      "db_artist": "Sabriye Erecepova",
      "path": "/Volumes/T9/1_dev/1_QO/myQO/navidrome/scripts/vk-music-scanner/downloads/Sabriye Erecepova/Sabriye Erecepova - Pamuqçı.mp3",
      "downloaded_at": "2025-12-25T11:39:50.018001"
    },
    {
      "artist": "Sabriye Erecepova",
      "title": "Port Artur",
      "db_artist": "Sabriye Erecepova",
      "path": "/Volumes/T9/1_dev/1_QO/myQO/navidrome/scripts/vk-music-scanner/downloads/Sabriye Erecepova/Sabriye Erecepova - Port Artur.mp3",
      "downloaded_at": "2025-12-25T11:39:52.896823"
    },
    {
      "artist": "Sabriye Erecepova",
      "title": "Quşaqlı qız",
      "db_artist": "Sabriye Erecepova",
      "path": "/Volumes/T9/1_dev/1_QO/myQO/navidrome/scripts/vk-music-scanner/downloads/Sabriye Erecepova/Sabriye Erecepova - Quşaqlı qız.mp3",
      "downloaded_at": "2025-12-25T11:40:20.422907"
    },
    {
      "artist": "Sabriye Erecepova",
      "title": "Nazli-nazli",
      "db_artist": "Sabriye Erecepova",
      "path": "/Volumes/T9/1_dev/1_QO/myQO/navidrome/scripts/vk-music-scanner/downloads/Sabriye Erecepova/Sabriye Erecepova - Nazli-nazli.mp3",
      "downloaded_at": "2025-12-25T11:40:23.668709"
    },
    {
      "artist": "Sabriye Erecepova",
      "title": "Bugun aynin",
      "db_artist": "Sabriye Erecepova",
      "path": "/Volumes/T9/1_dev/1_QO/myQO/navidrome/scripts/vk-music-scanner/downloads/Sabriye Erecepova/Sabriye Erecepova - Bugun aynin.mp3",
      "downloaded_at": "2025-12-25T11:40:26.487549"
    },
    {
      "artist": "Sabriye Erecepova",
      "title": "Kene aldı gam meni",
      "db_artist": "Sabriye Erecepova",
      "path": "/Volumes/T9/1_dev/1_QO/myQO/navidrome/scripts/vk-music-scanner/downloads/Sabriye Erecepova/Sabriye Erecepova - Kene aldı gam meni.mp3",
      "downloaded_at": "2025-12-25T11:40:36.183192"
    },
    {
      "artist": "Haytarma ansambli (Sabriye Erecepova)",
      "title": "Salıncaq",
      "db_artist": "Sabriye Erecepova",
      "path": "/Volumes/T9/1_dev/1_QO/myQO/navidrome/scripts/vk-music-scanner/downloads/Sabriye Erecepova/Haytarma ansambli (Sabriye Erecepova) - Salıncaq.mp3",
      "downloaded_at": "2025-12-25T11:40:38.545870"
    },
    {
      "artist": "Sabriye Erecepova",
      "title": "[Dağdan endi bir qozu]",
      "db_artist": "Sabriye Erecepova",
      "path": "/Volumes/T9/1_dev/1_QO/myQO/navidrome/scripts/vk-music-scanner/downloads/Sabriye Erecepova/Sabriye Erecepova - [Dağdan endi bir qozu].mp3",
      "downloaded_at": "2025-12-25T11:40:41.329144"
    },
    {
      "artist": "Sabriye Erecepova",
      "title": "Dereler shuma-shuma",
      "db_artist": "Sabriye Erecepova",
      "path": "/Volumes/T9/1_dev/1_QO/myQO/navidrome/scripts/vk-music-scanner/downloads/Sabriye Erecepova/Sabriye Erecepova - Dereler shuma-shuma.mp3",
      "downloaded_at": "2025-12-25T11:40:44.046821"
    },
    {
      "artist": "Akbikey",
      "title": "Salgir Boyu",
      "db_artist": "Selma Agat (Akbikey)",
      "path": "/Volumes/T9/1_dev/1_QO/myQO/navidrome/scripts/vk-music-scanner/downloads/Selma Agat (Akbikey)/Akbikey - Salgir Boyu.mp3",
      "downloaded_at": "2025-12-25T11:40:45.935157"
    },
    {
      "artist": "Selma Agat",
      "title": "Altı qızlar",
      "db_artist": "Selma Agat (Akbikey)",
      "path": "/Volumes/T9/1_dev/1_QO/myQO/navidrome/scripts/vk-music-scanner/downloads/Selma Agat (Akbikey)/Selma Agat - Altı qızlar.mp3",
      "downloaded_at": "2025-12-25T11:40:47.775223"
    },
    {
      "artist": "Akbikey",
      "title": "Karaker atim",
      "db_artist": "Selma Agat (Akbikey)",
      "path": "/Volumes/T9/1_dev/1_QO/myQO/navidrome/scripts/vk-music-scanner/downloads/Selma Agat (Akbikey)/Akbikey - Karaker atim.mp3",
      "downloaded_at": "2025-12-25T11:40:49.710064"
    },
    {
      "artist": "Server Kakura",
      "title": "Qırımım (Crimean)",
      "db_artist": "Server Kakura",
      "path": "/Volumes/T9/1_dev/1_QO/myQO/navidrome/scripts/vk-music-scanner/downloads/Server Kakura/Server Kakura - Qırımım (Crimean).mp3",
      "downloaded_at": "2025-12-25T11:40:54.058585"
    },
    {
      "artist": "Server Kakura",
      "title": "Agir ava",
      "db_artist": "Server Kakura",
      "path": "/Volumes/T9/1_dev/1_QO/myQO/navidrome/scripts/vk-music-scanner/downloads/Server Kakura/Server Kakura - Agir ava.mp3",
      "downloaded_at": "2025-12-25T11:40:56.157857"
    },
    {
      "artist": "SERVER KAKURA",
      "title": "DOKTUR CIVANIM",
      "db_artist": "Server Kakura",
      "path": "/Volumes/T9/1_dev/1_QO/myQO/navidrome/scripts/vk-music-scanner/downloads/Server Kakura/SERVER KAKURA - DOKTUR CIVANIM.mp3",
      "downloaded_at": "2025-12-25T11:40:58.584960"
    },
    {
      "artist": "ENVER BELALOV-SERVER KAKURA",
      "title": "RISTAL",
      "db_artist": "Server Kakura",
      "path": "/Volumes/T9/1_dev/1_QO/myQO/navidrome/scripts/vk-music-scanner/downloads/Server Kakura/ENVER BELALOV-SERVER KAKURA - RISTAL.mp3",
      "downloaded_at": "2025-12-25T11:41:01.293988"
    },
    {
      "artist": "Server Kakura",
      "title": "Трек 14",
      "db_artist": "Server Kakura",
      "path": "/Volumes/T9/1_dev/1_QO/myQO/navidrome/scripts/vk-music-scanner/downloads/Server Kakura/Server Kakura - Трек 14.mp3",
      "downloaded_at": "2025-12-25T11:41:03.459338"
    },
    {
      "artist": "Server Kakura",
      "title": "Ay-Petri haytarmasi",
      "db_artist": "Server Kakura",
      "path": "/Volumes/T9/1_dev/1_QO/myQO/navidrome/scripts/vk-music-scanner/downloads/Server Kakura/Server Kakura - Ay-Petri haytarmasi.mp3",
      "downloaded_at": "2025-12-25T11:41:06.059129"
    },
    {
      "artist": "SERVER KAKURA",
      "title": "BAHTLI OLUNIZ YASLAR",
      "db_artist": "Server Kakura",
      "path": "/Volumes/T9/1_dev/1_QO/myQO/navidrome/scripts/vk-music-scanner/downloads/Server Kakura/SERVER KAKURA - BAHTLI OLUNIZ YASLAR.mp3",
      "downloaded_at": "2025-12-25T11:41:08.393962"
    },
    {
      "artist": "SERVER KAKURA",
      "title": "CIBEREK CITIR-CITIR",
      "db_artist": "Server Kakura",
      "path": "/Volumes/T9/1_dev/1_QO/myQO/navidrome/scripts/vk-music-scanner/downloads/Server Kakura/SERVER KAKURA - CIBEREK CITIR-CITIR.mp3",
      "downloaded_at": "2025-12-25T11:41:11.788298"
    },
    {
      "artist": "Server Kakura",
      "title": "Bakçasaray kaytarması",
      "db_artist": "Server Kakura",
      "path": "/Volumes/T9/1_dev/1_QO/myQO/navidrome/scripts/vk-music-scanner/downloads/Server Kakura/Server Kakura - Bakçasaray kaytarması.mp3",
      "downloaded_at": "2025-12-25T11:41:13.772034"
    },
    {
      "artist": "SERVER KAKURA",
      "title": "DUGUN QAYTARMASI",
      "db_artist": "Server Kakura",
      "path": "/Volumes/T9/1_dev/1_QO/myQO/navidrome/scripts/vk-music-scanner/downloads/Server Kakura/SERVER KAKURA - DUGUN QAYTARMASI.mp3",
      "downloaded_at": "2025-12-25T11:41:15.811928"
    },
    {
      "artist": "Server Kakura",
      "title": "Amerika haytarması (3)",
      "db_artist": "Server Kakura",
      "path": "/Volumes/T9/1_dev/1_QO/myQO/navidrome/scripts/vk-music-scanner/downloads/Server Kakura/Server Kakura - Amerika haytarması (3).mp3",
      "downloaded_at": "2025-12-25T11:41:18.216924"
    },
    {
      "artist": "SERVER KAKURA",
      "title": "DOGGAN KUN BAYRAMI",
      "db_artist": "Server Kakura",
      "path": "/Volumes/T9/1_dev/1_QO/myQO/navidrome/scripts/vk-music-scanner/downloads/Server Kakura/SERVER KAKURA - DOGGAN KUN BAYRAMI.mp3",
      "downloaded_at": "2025-12-25T11:41:20.591237"
    },
    {
      "artist": "SERVER KAKURA",
      "title": "DEMIRCI-TEMIRCI",
      "db_artist": "Server Kakura",
      "path": "/Volumes/T9/1_dev/1_QO/myQO/navidrome/scripts/vk-music-scanner/downloads/Server Kakura/SERVER KAKURA - DEMIRCI-TEMIRCI.mp3",
      "downloaded_at": "2025-12-25T11:41:25.643778"
    },
    {
      "artist": "Sevil Memetova & Esken Zova",
      "title": "Elisa day's song (Where the wild roses grow)",
      "db_artist": "Sevil Memetova",
      "path": "/Volumes/T9/1_dev/1_QO/myQO/navidrome/scripts/vk-music-scanner/downloads/Sevil Memetova/Sevil Memetova & Esken Zova - Elisa day's song (Where the wild roses grow).mp3",
      "downloaded_at": "2025-12-25T11:41:29.178468"
    },
    {
      "artist": "Sevil Memetova",
      "title": "Dohtur (2)",
      "db_artist": "Sevil Memetova",
      "path": "/Volumes/T9/1_dev/1_QO/myQO/navidrome/scripts/vk-music-scanner/downloads/Sevil Memetova/Sevil Memetova - Dohtur (2).mp3",
      "downloaded_at": "2025-12-25T11:41:31.952661"
    },
    {
      "artist": "Sevil Memetova",
      "title": "Gitme, kal...",
      "db_artist": "Sevil Memetova",
      "path": "/Volumes/T9/1_dev/1_QO/myQO/navidrome/scripts/vk-music-scanner/downloads/Sevil Memetova/Sevil Memetova - Gitme, kal.mp3",
      "downloaded_at": "2025-12-25T11:41:35.593032"
    },
    {
      "artist": "Sevil Memetova",
      "title": "Jutro ( сербская )",
      "db_artist": "Sevil Memetova",
      "path": "/Volumes/T9/1_dev/1_QO/myQO/navidrome/scripts/vk-music-scanner/downloads/Sevil Memetova/Sevil Memetova - Jutro ( сербская ).mp3",
      "downloaded_at": "2025-12-25T11:41:37.880974"
    },
    {
      "artist": "Sevil Memetova (Seville) feat Adoni",
      "title": "Buriy",
      "db_artist": "Sevil Memetova",
      "path": "/Volumes/T9/1_dev/1_QO/myQO/navidrome/scripts/vk-music-scanner/downloads/Sevil Memetova/Sevil Memetova (Seville) feat Adoni - Buriy.mp3",
      "downloaded_at": "2025-12-25T11:41:40.167182"
    },
    {
      "artist": "Sevil Memetova",
      "title": "Gitme (не уходи)",
      "db_artist": "Sevil Memetova",
      "path": "/Volumes/T9/1_dev/1_QO/myQO/navidrome/scripts/vk-music-scanner/downloads/Sevil Memetova/Sevil Memetova - Gitme (не уходи).mp3",
      "downloaded_at": "2025-12-25T11:41:45.108239"
    },
    {
      "artist": "Sevil Memetova",
      "title": "Rijeka bez imena ( Река без имени)",
      "db_artist": "Sevil Memetova",
      "path": "/Volumes/T9/1_dev/1_QO/myQO/navidrome/scripts/vk-music-scanner/downloads/Sevil Memetova/Sevil Memetova - Rijeka bez imena ( Река без имени).mp3",
      "downloaded_at": "2025-12-25T11:41:47.537892"
    },
    {
      "artist": "Sevil Memetova & Erol  Büyükburç",
      "title": "Isnanbul",
      "db_artist": "Sevil Memetova",
      "path": "/Volumes/T9/1_dev/1_QO/myQO/navidrome/scripts/vk-music-scanner/downloads/Sevil Memetova/Sevil Memetova & Erol  Büyükburç - Isnanbul.mp3",
      "downloaded_at": "2025-12-25T11:41:50.180080"
    },
    {
      "artist": "Seyran 7'62 ve EmCiEl",
      "title": "Sen Qırımlısıñmı? (Panika yoq!)",
      "db_artist": "Seyran 7'62",
      "path": "/Volumes/T9/1_dev/1_QO/myQO/navidrome/scripts/vk-music-scanner/downloads/Seyran 7'62/Seyran 7'62 ve EmCiEl - Sen Qırımlısıñmı_ (Panika yoq!).mp3",
      "downloaded_at": "2025-12-25T11:41:53.275673"
    },
    {
      "artist": "Seyran 7'62",
      "title": "Ramazan ayı",
      "db_artist": "Seyran 7'62",
      "path": "/Volumes/T9/1_dev/1_QO/myQO/navidrome/scripts/vk-music-scanner/downloads/Seyran 7'62/Seyran 7'62 - Ramazan ayı.mp3",
      "downloaded_at": "2025-12-25T11:41:56.689829"
    },
    {
      "artist": "АРК (Гема, Kadar, Mecit, Seyran 7'62, Дым, Stem, Давчик, Буч, Marlen, M.J. Marley)",
      "title": "Крымский рэп",
      "db_artist": "Seyran 7'62",
      "path": "/Volumes/T9/1_dev/1_QO/myQO/navidrome/scripts/vk-music-scanner/downloads/Seyran 7'62/АРК (Гема, Kadar, Mecit, Seyran 7'62, Дым, Stem, Давчик, Буч, Marlen, M.J. Marley) - Крымский рэп.mp3",
      "downloaded_at": "2025-12-25T11:42:07.853369"
    },
    {
      "artist": "9. Гема (УО), Seyran (7'62), Вудига",
      "title": "Для раздумий",
      "db_artist": "Seyran 7'62",
      "path": "/Volumes/T9/1_dev/1_QO/myQO/navidrome/scripts/vk-music-scanner/downloads/Seyran 7'62/9. Гема (УО), Seyran (7'62), Вудига - Для раздумий.mp3",
      "downloaded_at": "2025-12-25T11:42:10.540547"
    },
    {
      "artist": "Seyran 7'62",
      "title": "Kim eger biz degil (крымскотатарский рэп)",
      "db_artist": "Seyran 7'62",
      "path": "/Volumes/T9/1_dev/1_QO/myQO/navidrome/scripts/vk-music-scanner/downloads/Seyran 7'62/Seyran 7'62 - Kim eger biz degil (крымскотатарский рэп).mp3",
      "downloaded_at": "2025-12-25T11:42:18.181886"
    },
    {
      "artist": "Seyran 7'62",
      "title": "ATR'ni öldürmeñiz! (FortRoyalBeatz)",
      "db_artist": "Seyran 7'62",
      "path": "/Volumes/T9/1_dev/1_QO/myQO/navidrome/scripts/vk-music-scanner/downloads/Seyran 7'62/Seyran 7'62 - ATR'ni öldürmeñiz! (FortRoyalBeatz).mp3",
      "downloaded_at": "2025-12-25T11:42:20.780158"
    },
    {
      "artist": "Seyran 7'62",
      "title": "Ramazan ayı (Azzy mash up)",
      "db_artist": "Seyran 7'62",
      "path": "/Volumes/T9/1_dev/1_QO/myQO/navidrome/scripts/vk-music-scanner/downloads/Seyran 7'62/Seyran 7'62 - Ramazan ayı (Azzy mash up).mp3",
      "downloaded_at": "2025-12-25T11:42:25.026505"
    },
    {
      "artist": "Seyran 7'62",
      "title": "Къырым, Ватан. Миллет",
      "db_artist": "Seyran 7'62",
      "path": "/Volumes/T9/1_dev/1_QO/myQO/navidrome/scripts/vk-music-scanner/downloads/Seyran 7'62/Seyran 7'62 - Къырым, Ватан. Миллет.mp3",
      "downloaded_at": "2025-12-25T11:42:28.782564"
    },
    {
      "artist": "Seyran 7'62",
      "title": "Unutılmaycaq facia",
      "db_artist": "Seyran 7'62",
      "path": "/Volumes/T9/1_dev/1_QO/myQO/navidrome/scripts/vk-music-scanner/downloads/Seyran 7'62/Seyran 7'62 - Unutılmaycaq facia.mp3",
      "downloaded_at": "2025-12-25T11:42:31.856498"
    },
    {
      "artist": "Seyran 7,62 MGL Afize Yusuf-kizi",
      "title": "1-intro 2-Qirimda yasha",
      "db_artist": "Seyran 7'62",
      "path": "/Volumes/T9/1_dev/1_QO/myQO/navidrome/scripts/vk-music-scanner/downloads/Seyran 7'62/Seyran 7,62 MGL Afize Yusuf-kizi - 1-intro 2-Qirimda yasha.mp3",
      "downloaded_at": "2025-12-25T11:42:34.095802"
    },
    {
      "artist": "Mashalladam|Seyran 7'62",
      "title": "Qırımda yaşa",
      "db_artist": "Seyran 7'62",
      "path": "/Volumes/T9/1_dev/1_QO/myQO/navidrome/scripts/vk-music-scanner/downloads/Seyran 7'62/Mashalladam_Seyran 7'62 - Qırımda yaşa.mp3",
      "downloaded_at": "2025-12-25T11:42:37.377845"
    },
    {
      "artist": "Seytabla Memetov",
      "title": "Amet-Han (CT)",
      "db_artist": "Seytabla Memetov",
      "path": "/Volumes/T9/1_dev/1_QO/myQO/navidrome/scripts/vk-music-scanner/downloads/Seytabla Memetov/Seytabla Memetov - Amet-Han (CT).mp3",
      "downloaded_at": "2025-12-25T11:42:40.053201"
    },
    {
      "artist": "SEYTABLA MEMETOV - SERVER KAKURA",
      "title": "KOTER BASINI - mars",
      "db_artist": "Seytabla Memetov",
      "path": "/Volumes/T9/1_dev/1_QO/myQO/navidrome/scripts/vk-music-scanner/downloads/Seytabla Memetov/SEYTABLA MEMETOV - SERVER KAKURA - KOTER BASINI - mars.mp3",
      "downloaded_at": "2025-12-25T11:42:42.412446"
    },
    {
      "artist": "Seytabla Memetov",
      "title": "Аметхан Султан",
      "db_artist": "Seytabla Memetov",
      "path": "/Volumes/T9/1_dev/1_QO/myQO/navidrome/scripts/vk-music-scanner/downloads/Seytabla Memetov/Seytabla Memetov - Аметхан Султан.mp3",
      "downloaded_at": "2025-12-25T11:42:46.754306"
    },
    {
      "artist": "Seytabla Memetov",
      "title": "Dostlar",
      "db_artist": "Seytabla Memetov",
      "path": "/Volumes/T9/1_dev/1_QO/myQO/navidrome/scripts/vk-music-scanner/downloads/Seytabla Memetov/Seytabla Memetov - Dostlar.mp3",
      "downloaded_at": "2025-12-25T11:42:49.288061"
    },
    {
      "artist": "Seytabla Memetov, Dilyaver Settarov, Edip Asanov",
      "title": "Tatarlığım dogğan erim",
      "db_artist": "Seytabla Memetov",
      "path": "/Volumes/T9/1_dev/1_QO/myQO/navidrome/scripts/vk-music-scanner/downloads/Seytabla Memetov/Seytabla Memetov, Dilyaver Settarov, Edip Asanov - Tatarlığım dogğan erim.mp3",
      "downloaded_at": "2025-12-25T11:42:51.372591"
    },
    {
      "artist": "ATR ANSAMBLİ VE SEYTABLA MEMETOV",
      "title": "bu yavluqnı",
      "db_artist": "Seytabla Memetov",
      "path": "/Volumes/T9/1_dev/1_QO/myQO/navidrome/scripts/vk-music-scanner/downloads/Seytabla Memetov/ATR ANSAMBLİ VE SEYTABLA MEMETOV - bu yavluqnı.mp3",
      "downloaded_at": "2025-12-25T11:42:54.136871"
    },
    {
      "artist": "Seytabla Memetov",
      "title": "Yalqızam yalqız (Sənə də qalmaz) (СТ)",
      "db_artist": "Seytabla Memetov",
      "path": "/Volumes/T9/1_dev/1_QO/myQO/navidrome/scripts/vk-music-scanner/downloads/Seytabla Memetov/Seytabla Memetov - Yalqızam yalqız (Sənə də qalmaz) (СТ).mp3",
      "downloaded_at": "2025-12-25T11:42:57.022265"
    },
    {
      "artist": "Susanna Memetova",
      "title": "Tañ yıldızı (Eski) (CT)",
      "db_artist": "Susanna Memetova",
      "path": "/Volumes/T9/1_dev/1_QO/myQO/navidrome/scripts/vk-music-scanner/downloads/Susanna Memetova/Susanna Memetova - Tañ yıldızı (Eski) (CT).mp3",
      "downloaded_at": "2025-12-25T11:42:59.043166"
    },
    {
      "artist": "Susanna Memetova",
      "title": "Dağdan da endi bir qozu",
      "db_artist": "Susanna Memetova",
      "path": "/Volumes/T9/1_dev/1_QO/myQO/navidrome/scripts/vk-music-scanner/downloads/Susanna Memetova/Susanna Memetova - Dağdan da endi bir qozu.mp3",
      "downloaded_at": "2025-12-25T11:43:02.510274"
    },
    {
      "artist": "Susanna Memetova",
      "title": "Alie",
      "db_artist": "Susanna Memetova",
      "path": "/Volumes/T9/1_dev/1_QO/myQO/navidrome/scripts/vk-music-scanner/downloads/Susanna Memetova/Susanna Memetova - Alie.mp3",
      "downloaded_at": "2025-12-25T11:44:20.015537"
    },
    {
      "artist": "Susanna Memetova",
      "title": "Evleri bar suv başında",
      "db_artist": "Susanna Memetova",
      "path": "/Volumes/T9/1_dev/1_QO/myQO/navidrome/scripts/vk-music-scanner/downloads/Susanna Memetova/Susanna Memetova - Evleri bar suv başında.mp3",
      "downloaded_at": "2025-12-25T11:44:22.327629"
    },
    {
      "artist": "Susanna Memetova",
      "title": "Pencereden (CT)",
      "db_artist": "Susanna Memetova",
      "path": "/Volumes/T9/1_dev/1_QO/myQO/navidrome/scripts/vk-music-scanner/downloads/Susanna Memetova/Susanna Memetova - Pencereden (CT).mp3",
      "downloaded_at": "2025-12-25T11:44:24.432921"
    },
    {
      "artist": "Uryane Kenjikayeva ve Zarema Paday",
      "title": "Qamışım",
      "db_artist": "Uryane Kenjikayeva",
      "path": "/Volumes/T9/1_dev/1_QO/myQO/navidrome/scripts/vk-music-scanner/downloads/Uryane Kenjikayeva/Uryane Kenjikayeva ve Zarema Paday - Qamışım.mp3",
      "downloaded_at": "2025-12-25T11:44:26.911321"
    },
    {
      "artist": "Uryane Kenjikayeva",
      "title": "Aqmescit",
      "db_artist": "Uryane Kenjikayeva",
      "path": "/Volumes/T9/1_dev/1_QO/myQO/navidrome/scripts/vk-music-scanner/downloads/Uryane Kenjikayeva/Uryane Kenjikayeva - Aqmescit.mp3",
      "downloaded_at": "2025-12-25T11:44:29.507170"
    },
    {
      "artist": "Zarema Hanum",
      "title": "www.Sattarov.net",
      "db_artist": "Zarema Hanum",
      "path": "/Volumes/T9/1_dev/1_QO/myQO/navidrome/scripts/vk-music-scanner/downloads/Zarema Hanum/Zarema Hanum - www.Sattarov.net.mp3",
      "downloaded_at": "2025-12-25T11:44:32.189394"
    },
    {
      "artist": "Zarema Hanum",
      "title": "Hamsi qoydım tavaya (CT)",
      "db_artist": "Zarema Hanum",
      "path": "/Volumes/T9/1_dev/1_QO/myQO/navidrome/scripts/vk-music-scanner/downloads/Zarema Hanum/Zarema Hanum - Hamsi qoydım tavaya (CT).mp3",
      "downloaded_at": "2025-12-25T11:44:34.543077"
    },
    {
      "artist": "Zarema Hanum",
      "title": "AudioTrack 11",
      "db_artist": "Zarema Hanum",
      "path": "/Volumes/T9/1_dev/1_QO/myQO/navidrome/scripts/vk-music-scanner/downloads/Zarema Hanum/Zarema Hanum - AudioTrack 11.mp3",
      "downloaded_at": "2025-12-25T11:44:37.085768"
    },
    {
      "artist": "Zarema Hanum",
      "title": "Hamse",
      "db_artist": "Zarema Hanum",
      "path": "/Volumes/T9/1_dev/1_QO/myQO/navidrome/scripts/vk-music-scanner/downloads/Zarema Hanum/Zarema Hanum - Hamse.mp3",
      "downloaded_at": "2025-12-25T11:44:39.543490"
    },
    {
      "artist": "ZAREMA HANUM",
      "title": "Ягъма ягъмур",
      "db_artist": "Zarema Hanum",
      "path": "/Volumes/T9/1_dev/1_QO/myQO/navidrome/scripts/vk-music-scanner/downloads/Zarema Hanum/ZAREMA HANUM - Ягъма ягъмур.mp3",
      "downloaded_at": "2025-12-25T11:44:42.568873"
    },
    {
      "artist": "Zarema Hanum",
      "title": "Qaleniñ tübünde",
      "db_artist": "Zarema Hanum",
      "path": "/Volumes/T9/1_dev/1_QO/myQO/navidrome/scripts/vk-music-scanner/downloads/Zarema Hanum/Zarema Hanum - Qaleniñ tübünde.mp3",
      "downloaded_at": "2025-12-25T11:44:44.892778"
    },
    {
      "artist": "Zarema Hanum",
      "title": "Elimdeki kemane(Azzy rework)",
      "db_artist": "Zarema Hanum",
      "path": "/Volumes/T9/1_dev/1_QO/myQO/navidrome/scripts/vk-music-scanner/downloads/Zarema Hanum/Zarema Hanum - Elimdeki kemane(Azzy rework).mp3",
      "downloaded_at": "2025-12-25T11:44:47.534940"
    },
    {
      "artist": "Zeynep",
      "title": "Neuanfang",
      "db_artist": "Zeynep Lömanova",
      "path": "/Volumes/T9/1_dev/1_QO/myQO/navidrome/scripts/vk-music-scanner/downloads/Zeynep Lömanova/Zeynep - Neuanfang.mp3",
      "downloaded_at": "2025-12-25T11:44:50.204242"
    },
    {
      "artist": "Zeynep",
      "title": "Keine Träne",
      "db_artist": "Zeynep Lömanova",
      "path": "/Volumes/T9/1_dev/1_QO/myQO/navidrome/scripts/vk-music-scanner/downloads/Zeynep Lömanova/Zeynep - Keine Träne.mp3",
      "downloaded_at": "2025-12-25T11:44:52.519745"
    },
    {
      "artist": "Zore Kadıyeva",
      "title": "Degirmenköy",
      "db_artist": "Zore Kadıyeva",
      "path": "/Volumes/T9/1_dev/1_QO/myQO/navidrome/scripts/vk-music-scanner/downloads/Zore Kadıyeva/Zore Kadıyeva - Degirmenköy.mp3",
      "downloaded_at": "2025-12-25T11:44:54.713325"
    },
    {
      "artist": "Zore Kadıyeva",
      "title": "Ah, kelinim (N I Y E T)",
      "db_artist": "Zore Kadıyeva",
      "path": "/Volumes/T9/1_dev/1_QO/myQO/navidrome/scripts/vk-music-scanner/downloads/Zore Kadıyeva/Zore Kadıyeva - Ah, kelinim (N I Y E T).mp3",
      "downloaded_at": "2025-12-25T11:44:57.355931"
    },
    {
      "artist": "Raziye Seytablayeva ve ATR ansambli",
      "title": "Bağçalarda börülce",
      "db_artist": "ATR ansambli",
      "path": "/Volumes/T9/1_dev/1_QO/myQO/navidrome/scripts/vk-music-scanner/downloads/ATR ansambli/Raziye Seytablayeva ve ATR ansambli - Bağçalarda börülce.mp3",
      "downloaded_at": "2026-01-07T14:16:55.615198"
    },
    {
      "artist": "ATR ansambli",
      "title": "Saba erte",
      "db_artist": "ATR ansambli",
      "path": "/Volumes/T9/1_dev/1_QO/myQO/navidrome/scripts/vk-music-scanner/downloads/ATR ansambli/ATR ansambli - Saba erte.mp3",
      "downloaded_at": "2026-01-07T14:16:59.276887"
    },
    {
      "artist": "Afize Kassara ve ATR ansambli",
      "title": "Ben giderim Batuma",
      "db_artist": "ATR ansambli",
      "path": "/Volumes/T9/1_dev/1_QO/myQO/navidrome/scripts/vk-music-scanner/downloads/ATR ansambli/Afize Kassara ve ATR ansambli - Ben giderim Batuma.mp3",
      "downloaded_at": "2026-01-07T14:17:02.044946"
    },
    {
      "artist": "Alim Osmanov (Qara Deñiz)",
      "title": "В Симферополе (live)",
      "db_artist": "Alim Osmanov (Qara Deñiz)",
      "path": "/Volumes/T9/1_dev/1_QO/myQO/navidrome/scripts/vk-music-scanner/downloads/Alim Osmanov (Qara Deñiz)/Alim Osmanov (Qara Deñiz) - В Симферополе (live).mp3",
      "downloaded_at": "2026-01-07T14:17:04.614313"
    },
    {
      "artist": "Arsen Osmanov & Enver Zaman",
      "title": "Yani Yil 2022",
      "db_artist": "Arsen Osmanov",
      "path": "/Volumes/T9/1_dev/1_QO/myQO/navidrome/scripts/vk-music-scanner/downloads/Arsen Osmanov/Arsen Osmanov & Enver Zaman - Yani Yil 2022.mp3",
      "downloaded_at": "2026-01-07T14:17:07.933671"
    },
    {
      "artist": "Emil Memetov ve Asiye Saale",
      "title": "ARU haytarması",
      "db_artist": "Asiye Saale",
      "path": "/Volumes/T9/1_dev/1_QO/myQO/navidrome/scripts/vk-music-scanner/downloads/Asiye Saale/Emil Memetov ve Asiye Saale - ARU haytarması.mp3",
      "downloaded_at": "2026-01-07T14:17:11.225581"
    },
    {
      "artist": "Balalar",
      "title": "Baar",
      "db_artist": "Balalar",
      "path": "/Volumes/T9/1_dev/1_QO/myQO/navidrome/scripts/vk-music-scanner/downloads/Balalar/Balalar - Baar.mp3",
      "downloaded_at": "2026-01-07T14:17:13.913821"
    },
    {
      "artist": "Нариман Балич ве Dj Bebek",
      "title": "Яшлар авасы",
      "db_artist": "DJ Bebek",
      "path": "/Volumes/T9/1_dev/1_QO/myQO/navidrome/scripts/vk-music-scanner/downloads/DJ Bebek/Нариман Балич ве Dj Bebek - Яшлар авасы.mp3",
      "downloaded_at": "2026-01-07T14:17:17.163479"
    },
    {
      "artist": "dj bebek & Эльзара Баталова",
      "title": "Эй Оглан (radio edit 2011)",
      "db_artist": "DJ Bebek",
      "path": "/Volumes/T9/1_dev/1_QO/myQO/navidrome/scripts/vk-music-scanner/downloads/DJ Bebek/dj bebek & Эльзара Баталова - Эй Оглан (radio edit 2011).mp3",
      "downloaded_at": "2026-01-07T14:17:20.692525"
    },
    {
      "artist": "Эльнара Кучук feat. Dj Bebek",
      "title": "Къызылчыкълар",
      "db_artist": "DJ Bebek",
      "path": "/Volumes/T9/1_dev/1_QO/myQO/navidrome/scripts/vk-music-scanner/downloads/DJ Bebek/Эльнара Кучук feat. Dj Bebek - Къызылчыкълар.mp3",
      "downloaded_at": "2026-01-07T14:17:25.326731"
    },
    {
      "artist": "dj bebek",
      "title": "dj Bebek Qaitarmasi (produced by dj bebek 2016)",
      "db_artist": "DJ Bebek",
      "path": "/Volumes/T9/1_dev/1_QO/myQO/navidrome/scripts/vk-music-scanner/downloads/DJ Bebek/dj bebek - dj Bebek Qaitarmasi (produced by dj bebek 2016).mp3",
      "downloaded_at": "2026-01-07T14:17:29.171511"
    },
    {
      "artist": "Nariman Baliз ve DJ Bebek",
      "title": "Maalla haytarmas",
      "db_artist": "DJ Bebek",
      "path": "/Volumes/T9/1_dev/1_QO/myQO/navidrome/scripts/vk-music-scanner/downloads/DJ Bebek/Nariman Baliз ve DJ Bebek - Maalla haytarmas.mp3",
      "downloaded_at": "2026-01-07T14:17:33.600514"
    },
    {
      "artist": "Nariman Baliç ve DJ Bebek",
      "title": "Dostlar avası",
      "db_artist": "DJ Bebek",
      "path": "/Volumes/T9/1_dev/1_QO/myQO/navidrome/scripts/vk-music-scanner/downloads/DJ Bebek/Nariman Baliç ve DJ Bebek - Dostlar avası.mp3",
      "downloaded_at": "2026-01-07T14:17:36.321727"
    },
    {
      "artist": "Нариман Балич ве Dj Bebek",
      "title": "Той авасы танец в школе3",
      "db_artist": "DJ Bebek",
      "path": "/Volumes/T9/1_dev/1_QO/myQO/navidrome/scripts/vk-music-scanner/downloads/DJ Bebek/Нариман Балич ве Dj Bebek - Той авасы танец в школе3.mp3",
      "downloaded_at": "2026-01-07T14:17:38.774575"
    },
    {
      "artist": "Нариман Балич ве Dj Bebek",
      "title": "Машалла хайтармасы",
      "db_artist": "DJ Bebek",
      "path": "/Volumes/T9/1_dev/1_QO/myQO/navidrome/scripts/vk-music-scanner/downloads/DJ Bebek/Нариман Балич ве Dj Bebek - Машалла хайтармасы.mp3",
      "downloaded_at": "2026-01-07T14:17:42.107004"
    },
    {
      "artist": "DJ BEBEK",
      "title": "радио Meydan",
      "db_artist": "DJ Bebek",
      "path": "/Volumes/T9/1_dev/1_QO/myQO/navidrome/scripts/vk-music-scanner/downloads/DJ Bebek/DJ BEBEK - радио Meydan.mp3",
      "downloaded_at": "2026-01-07T14:17:45.449657"
    },
    {
      "artist": "DJ BEBEK",
      "title": "радио Мейдан",
      "db_artist": "DJ Bebek",
      "path": "/Volumes/T9/1_dev/1_QO/myQO/navidrome/scripts/vk-music-scanner/downloads/DJ Bebek/DJ BEBEK - радио Мейдан.mp3",
      "downloaded_at": "2026-01-07T14:17:49.506405"
    },
    {
      "artist": "Диляра Махмудова/ Dilâra Mahmudova_DagJi music \"Seniñ içün\" (2015)",
      "title": "\"Seniñ içün\" / Сенинъ ичун (Prod. Tematik 2015)",
      "db_artist": "Dilâra Mahmudova",
      "path": "/Volumes/T9/1_dev/1_QO/myQO/navidrome/scripts/vk-music-scanner/downloads/Dilâra Mahmudova/Диляра Махмудова_ Dilâra Mahmudova_DagJi music _Seniñ içün_ (2015) - _Seniñ içün_ _ Сенинъ ичун (Prod. Tematik 2015).mp3",
      "downloaded_at": "2026-01-07T14:17:52.369202"
    },
    {
      "artist": "OsMan",
      "title": "Wet",
      "db_artist": "Dilâver Osmanov",
      "path": "/Volumes/T9/1_dev/1_QO/myQO/navidrome/scripts/vk-music-scanner/downloads/Dilâver Osmanov/OsMan - Wet.mp3",
      "downloaded_at": "2026-01-07T14:17:55.403881"
    },
    {
      "artist": "OsMan",
      "title": "Dr.UGS",
      "db_artist": "Dilâver Osmanov",
      "path": "/Volumes/T9/1_dev/1_QO/myQO/navidrome/scripts/vk-music-scanner/downloads/Dilâver Osmanov/OsMan - Dr.UGS.mp3",
      "downloaded_at": "2026-01-07T14:17:58.841329"
    },
    {
      "artist": "Dilaver Osmanov",
      "title": "Karadeniz",
      "db_artist": "Dilâver Osmanov",
      "path": "/Volumes/T9/1_dev/1_QO/myQO/navidrome/scripts/vk-music-scanner/downloads/Dilâver Osmanov/Dilaver Osmanov - Karadeniz.mp3",
      "downloaded_at": "2026-01-07T14:18:00.971393"
    },
    {
      "artist": "Elzara Batalova",
      "title": "Sabriye (CT)",
      "db_artist": "Elzara Batalova",
      "path": "/Volumes/T9/1_dev/1_QO/myQO/navidrome/scripts/vk-music-scanner/downloads/Elzara Batalova/Elzara Batalova - Sabriye (CT).mp3",
      "downloaded_at": "2026-01-07T14:18:03.921172"
    },
    {
      "artist": "Elzara Batalova",
      "title": "Yalta",
      "db_artist": "Elzara Batalova",
      "path": "/Volumes/T9/1_dev/1_QO/myQO/navidrome/scripts/vk-music-scanner/downloads/Elzara Batalova/Elzara Batalova - Yalta.mp3",
      "downloaded_at": "2026-01-07T14:18:06.709533"
    },
    {
      "artist": "Emine Mustafayeva",
      "title": "Üç gögercin (minus)",
      "db_artist": "Emine Mustafayeva",
      "path": "/Volumes/T9/1_dev/1_QO/myQO/navidrome/scripts/vk-music-scanner/downloads/Emine Mustafayeva/Emine Mustafayeva - Üç gögercin (minus).mp3",
      "downloaded_at": "2026-01-07T14:18:09.218433"
    },
    {
      "artist": "Emine Mustafayeva",
      "title": "Qaleniñ tübünde (СТ)",
      "db_artist": "Emine Mustafayeva",
      "path": "/Volumes/T9/1_dev/1_QO/myQO/navidrome/scripts/vk-music-scanner/downloads/Emine Mustafayeva/Emine Mustafayeva - Qaleniñ tübünde (СТ).mp3",
      "downloaded_at": "2026-01-07T14:18:11.732663"
    },
    {
      "artist": "Selami Sahin& Burcu Gunes",
      "title": "Ben Birtek Kadin Sevdim",
      "db_artist": "Güneş",
      "path": "/Volumes/T9/1_dev/1_QO/myQO/navidrome/scripts/vk-music-scanner/downloads/Güneş/Selami Sahin& Burcu Gunes - Ben Birtek Kadin Sevdim.mp3",
      "downloaded_at": "2026-01-07T14:18:15.787776"
    },
    {
      "artist": "Burcu Gunes",
      "title": "Sahilden",
      "db_artist": "Güneş",
      "path": "/Volumes/T9/1_dev/1_QO/myQO/navidrome/scripts/vk-music-scanner/downloads/Güneş/Burcu Gunes - Sahilden.mp3",
      "downloaded_at": "2026-01-07T14:18:18.572932"
    },
    {
      "artist": "DEEP HOUSE | Ugur Can Yenal, Gunes Taskiran",
      "title": "You Against Me (Original Mix)",
      "db_artist": "Güneş",
      "path": "/Volumes/T9/1_dev/1_QO/myQO/navidrome/scripts/vk-music-scanner/downloads/Güneş/DEEP HOUSE _ Ugur Can Yenal, Gunes Taskiran - You Against Me (Original Mix).mp3",
      "downloaded_at": "2026-01-07T14:18:21.690125"
    },
    {
      "artist": "Jamala feat. alyona alyona",
      "title": "Забирай",
      "db_artist": "Jamala",
      "path": "/Volumes/T9/1_dev/1_QO/myQO/navidrome/scripts/vk-music-scanner/downloads/Jamala/Jamala feat. alyona alyona - Забирай.mp3",
      "downloaded_at": "2026-01-07T14:18:25.409181"
    },
    {
      "artist": "Jamala",
      "title": "Иные (Танцы на ТНТ, 3 сезон)",
      "db_artist": "Jamala",
      "path": "/Volumes/T9/1_dev/1_QO/myQO/navidrome/scripts/vk-music-scanner/downloads/Jamala/Jamala - Иные (Танцы на ТНТ, 3 сезон).mp3",
      "downloaded_at": "2026-01-07T14:18:29.102034"
    },
    {
      "artist": "Jamala",
      "title": "Жалi (feat. Alyona Alyona)",
      "db_artist": "Jamala",
      "path": "/Volumes/T9/1_dev/1_QO/myQO/navidrome/scripts/vk-music-scanner/downloads/Jamala/Jamala - Жалi (feat. Alyona Alyona).mp3",
      "downloaded_at": "2026-01-07T14:18:33.070538"
    },
    {
      "artist": "Jamala (Джамала)",
      "title": "I'm Like a Bird (All or Nothing '2013)",
      "db_artist": "Jamala",
      "path": "/Volumes/T9/1_dev/1_QO/myQO/navidrome/scripts/vk-music-scanner/downloads/Jamala/Jamala (Джамала) - I'm Like a Bird (All or Nothing '2013).mp3",
      "downloaded_at": "2026-01-07T14:18:35.776589"
    },
    {
      "artist": "Jamala (Джамала)",
      "title": "1944 (Евровидение 2016 Украина)",
      "db_artist": "Jamala",
      "path": "/Volumes/T9/1_dev/1_QO/myQO/navidrome/scripts/vk-music-scanner/downloads/Jamala/Jamala (Джамала) - 1944 (Евровидение 2016 Украина).mp3",
      "downloaded_at": "2026-01-07T14:18:39.522376"
    },
    {
      "artist": "Jamala",
      "title": "Сумую (Morphom Remix)",
      "db_artist": "Jamala",
      "path": "/Volumes/T9/1_dev/1_QO/myQO/navidrome/scripts/vk-music-scanner/downloads/Jamala/Jamala - Сумую (Morphom Remix).mp3",
      "downloaded_at": "2026-01-07T14:18:42.749178"
    },
    {
      "artist": "Nariman Balic",
      "title": "Borino oro",
      "db_artist": "Nariman Baliç",
      "path": "/Volumes/T9/1_dev/1_QO/myQO/navidrome/scripts/vk-music-scanner/downloads/Nariman Baliç/Nariman Balic - Borino oro.mp3",
      "downloaded_at": "2026-01-07T14:18:45.706771"
    },
    {
      "artist": "Nariman Balich",
      "title": "Sefer",
      "db_artist": "Nariman Baliç",
      "path": "/Volumes/T9/1_dev/1_QO/myQO/navidrome/scripts/vk-music-scanner/downloads/Nariman Baliç/Nariman Balich - Sefer.mp3",
      "downloaded_at": "2026-01-07T14:18:49.348819"
    },
    {
      "artist": "Nariman Balich",
      "title": "Şeñ Haytarma (feat. Aliye Bekirova)",
      "db_artist": "Nariman Baliç",
      "path": "/Volumes/T9/1_dev/1_QO/myQO/navidrome/scripts/vk-music-scanner/downloads/Nariman Baliç/Nariman Balich - Şeñ Haytarma (feat. Aliye Bekirova).mp3",
      "downloaded_at": "2026-01-07T14:18:52.961429"
    },
    {
      "artist": "Qarasuv",
      "title": "Ayşem",
      "db_artist": "Qarasuv",
      "path": "/Volumes/T9/1_dev/1_QO/myQO/navidrome/scripts/vk-music-scanner/downloads/Qarasuv/Qarasuv - Ayşem.mp3",
      "downloaded_at": "2026-01-07T14:18:55.243921"
    },
    {
      "artist": "Qarasuv",
      "title": "Aydı da canım",
      "db_artist": "Qarasuv",
      "path": "/Volumes/T9/1_dev/1_QO/myQO/navidrome/scripts/vk-music-scanner/downloads/Qarasuv/Qarasuv - Aydı da canım.mp3",
      "downloaded_at": "2026-01-07T14:18:58.029333"
    },
    {
      "artist": "Qırım toy avası",
      "title": "Dolu",
      "db_artist": "Qırım",
      "path": "/Volumes/T9/1_dev/1_QO/myQO/navidrome/scripts/vk-music-scanner/downloads/Qırım/Qırım toy avası - Dolu.mp3",
      "downloaded_at": "2026-01-07T14:19:00.478657"
    },
    {
      "artist": "Reyana Kadırova ve Maqam",
      "title": "Ketirdiler Kevseri (İlâhi)",
      "db_artist": "Reyana Kadırova",
      "path": "/Volumes/T9/1_dev/1_QO/myQO/navidrome/scripts/vk-music-scanner/downloads/Reyana Kadırova/Reyana Kadırova ve Maqam - Ketirdiler Kevseri (İlâhi).mp3",
      "downloaded_at": "2026-01-07T14:19:02.946503"
    },
    {
      "artist": "Rustem Memetov",
      "title": "Vatan Qırım",
      "db_artist": "Rustem Memetov",
      "path": "/Volumes/T9/1_dev/1_QO/myQO/navidrome/scripts/vk-music-scanner/downloads/Rustem Memetov/Rustem Memetov - Vatan Qırım.mp3",
      "downloaded_at": "2026-01-07T14:19:05.914125"
    },
    {
      "artist": "Sabriye Erecepova",
      "title": "Tütüncü Qız",
      "db_artist": "Sabriye Erecepova",
      "path": "/Volumes/T9/1_dev/1_QO/myQO/navidrome/scripts/vk-music-scanner/downloads/Sabriye Erecepova/Sabriye Erecepova - Tütüncü Qız.mp3",
      "downloaded_at": "2026-01-07T14:19:13.268057"
    },
    {
      "artist": "Server Kakura",
      "title": "Хайырлы яшлар олсун!",
      "db_artist": "Server Kakura",
      "path": "/Volumes/T9/1_dev/1_QO/myQO/navidrome/scripts/vk-music-scanner/downloads/Server Kakura/Server Kakura - Хайырлы яшлар олсун!.mp3",
      "downloaded_at": "2026-01-07T14:19:15.890116"
    },
    {
      "artist": "SERVER KAKURA",
      "title": "sabalar hayır",
      "db_artist": "Server Kakura",
      "path": "/Volumes/T9/1_dev/1_QO/myQO/navidrome/scripts/vk-music-scanner/downloads/Server Kakura/SERVER KAKURA - sabalar hayır.mp3",
      "downloaded_at": "2026-01-07T14:19:18.458886"
    },
    {
      "artist": "Server Kakura",
      "title": "Bayrağım (CT)",
      "db_artist": "Server Kakura",
      "path": "/Volumes/T9/1_dev/1_QO/myQO/navidrome/scripts/vk-music-scanner/downloads/Server Kakura/Server Kakura - Bayrağım (CT).mp3",
      "downloaded_at": "2026-01-07T14:19:21.549907"
    },
    {
      "artist": "Sevil Memetova",
      "title": "Dohtur civanım (Live)",
      "db_artist": "Sevil Memetova",
      "path": "/Volumes/T9/1_dev/1_QO/myQO/navidrome/scripts/vk-music-scanner/downloads/Sevil Memetova/Sevil Memetova - Dohtur civanım (Live).mp3",
      "downloaded_at": "2026-01-07T14:19:25.516947"
    },
    {
      "artist": "Seyran 7'62",
      "title": "Noqtai nazarım (крымскотатарский рэп)",
      "db_artist": "Seyran 7'62",
      "path": "/Volumes/T9/1_dev/1_QO/myQO/navidrome/scripts/vk-music-scanner/downloads/Seyran 7'62/Seyran 7'62 - Noqtai nazarım (крымскотатарский рэп).mp3",
      "downloaded_at": "2026-01-07T14:19:29.225445"
    },
    {
      "artist": "Seyran 7'62",
      "title": "Böyle olurmı aslı?",
      "db_artist": "Seyran 7'62",
      "path": "/Volumes/T9/1_dev/1_QO/myQO/navidrome/scripts/vk-music-scanner/downloads/Seyran 7'62/Seyran 7'62 - Böyle olurmı aslı_.mp3",
      "downloaded_at": "2026-01-07T14:19:31.965708"
    },
    {
      "artist": "Seyran 7’62,  Dilyara Mahmudova-Dagzhi, MGL, Elyana Ablyazimova, Dmitry Bosulaev, Elena Kotnisheva, Feride Ablyazova",
      "title": "Vatanim Qırım",
      "db_artist": "Seyran 7'62",
      "path": "/Volumes/T9/1_dev/1_QO/myQO/navidrome/scripts/vk-music-scanner/downloads/Seyran 7'62/Seyran 7’62,  Dilyara Mahmudova-Dagzhi, MGL, Elyana Ablyazimova, Dmitry Bosulaev, Elena Kotnisheva, Feride Ablyazova - Vatanim Qırım.mp3",
      "downloaded_at": "2026-01-07T14:19:35.563995"
    },
    {
      "artist": "Susanna Memetova",
      "title": "Ural dağı (N I Y E T)",
      "db_artist": "Susanna Memetova",
      "path": "/Volumes/T9/1_dev/1_QO/myQO/navidrome/scripts/vk-music-scanner/downloads/Susanna Memetova/Susanna Memetova - Ural dağı (N I Y E T).mp3",
      "downloaded_at": "2026-01-07T14:19:38.846408"
    },
    {
      "artist": "Susanna Memetova",
      "title": "Vatan aqqında",
      "db_artist": "Susanna Memetova",
      "path": "/Volumes/T9/1_dev/1_QO/myQO/navidrome/scripts/vk-music-scanner/downloads/Susanna Memetova/Susanna Memetova - Vatan aqqında.mp3",
      "downloaded_at": "2026-01-07T14:19:41.451156"
    }
  ],
  "last_run": "2026-01-07T14:22:07.623572"
}